Workbook

Sheet Controle PCs
A1: Data Última Aprovação RC | B1: Data Pedido | C1: SLA Atendimento | D1: Comprador | E1: Área Requisitante | F1: Fornecedor | G1: Tipo | H1: Material / Serviço | I1: SLA Padrão | J1: Atrasada / No prazo | K1: Δ SLA Padrão x SLA Atendimento | L1: Preço Histórico | M1: Proposta Inicial | N1: Proposta Negociada | O1: Moeda | P1: Saving + Cost Total | Q1: % Redução | R1: Modalidade | S1: RC | T1: Pedido Compras | U1: Previsão Entrega | V1: Follow Up | W1: NF | X1: RECEBIMENTO CONCLUÍDO? | Y1: FORNECEDOR LOCAL?
A2: 46209 | B2: 46206 | C2: =IF(OR(A2="",B2=""),"",B2-A2) -> -3 | D2: Amanda Salvi | E2: ADMINISTRATIVE | F2: Disk Limpeza Total Ltda | G2: Spot | H2: Material Urgente | I2: =IFERROR(VLOOKUP(H2,SLA_Ref!$A$1:$B$8,2,FALSE),"") -> 3 | J2: =IF(A2="","",IF(B2="",IF(TODAY()-A2>I2,"ATRASADA","EM ANDAMENTO"),IF(B2-A2>I2,"ATRASADA","NO PRAZO"))) -> NO PRAZO | K2: =Tabela2[[#This Row],[SLA Padrão]]-Tabela2[[#This Row],[SLA Atendimento]] -> 6 | M2: 448.01 | N2: 448.01 | O2: BRL | P2: =Tabela2[[#This Row],[Proposta Inicial]]-Tabela2[[#This Row],[Proposta Negociada]] -> 0 | Q2: =Tabela2[[#This Row],[Proposta Negociada]]/Tabela2[[#This Row],[Proposta Inicial]]-1 -> 0 | S2: RC 10001693 | T2: 450000024 | X2: Sim | Y2: Sim
A3: 46209 | B3: 46204 | C3: =IF(OR(A3="",B3=""),"",B3-A3) -> -5 | D3: Amanda Salvi | E3: ADMINISTRATIVE | F3: Idealiza Comercio de Utilidades Ltda | G3: Spot | H3: Material Urgente | I3: =IFERROR(VLOOKUP(H3,SLA_Ref!$A$1:$B$8,2,FALSE),"") -> 3 | J3: =IF(A3="","",IF(B3="",IF(TODAY()-A3>I3,"ATRASADA","EM ANDAMENTO"),IF(B3-A3>I3,"ATRASADA","NO PRAZO"))) -> NO PRAZO | K3: =Tabela2[[#This Row],[SLA Padrão]]-Tabela2[[#This Row],[SLA Atendimento]] -> 8 | M3: 51.9 | N3: 51.9 | O3: BRL | P3: =Tabela2[[#This Row],[Proposta Inicial]]-Tabela2[[#This Row],[Proposta Negociada]] -> 0 | Q3: =Tabela2[[#This Row],[Proposta Negociada]]/Tabela2[[#This Row],[Proposta Inicial]]-1 -> 0 | S3: RC 10001694 | T3: 450000024 | X3: Sim | Y3: Não
A4: 46202 | B4: 46205 | C4: =IF(OR(A4="",B4=""),"",B4-A4) -> 3 | D4: Michel Bernardes | E4: PROJECTS | F4: Mcr Plataformas | G4: Contrato | H4: Contrato Contínuo Simples | I4: =IFERROR(VLOOKUP(H4,SLA_Ref!$A$1:$B$8,2,FALSE),"") -> 30 | J4: =IF(A4="","",IF(B4="",IF(TODAY()-A4>I4,"ATRASADA","EM ANDAMENTO"),IF(B4-A4>I4,"ATRASADA","NO PRAZO"))) -> NO PRAZO | K4: =Tabela2[[#This Row],[SLA Padrão]]-Tabela2[[#This Row],[SLA Atendimento]] -> 27 | L4: 5900 | M4: =5900*12 -> 70800 | N4: =4200*12 -> 50400 | O4: BRL | P4: =Tabela2[[#This Row],[Proposta Inicial]]-Tabela2[[#This Row],[Proposta Negociada]] -> 20400 | Q4: =Tabela2[[#This Row],[Proposta Negociada]]/Tabela2[[#This Row],[Proposta Inicial]]-1 -> -0.28813559 | R4: Saving | S4: Locação PTA- Transferência de Contrato | T4: 450000170 | W4: 148 | X4: Mensal | Y4: Sim
A5: 46199 | B5: 46204 | C5: =IF(OR(A5="",B5=""),"",B5-A5) -> 5 | D5: Michel Bernardes | E5: GEOLOGICAL EXPLORATION | F5: Alpha Abras | G5: Spot | H5: Material Normal | I5: =IFERROR(VLOOKUP(H5,SLA_Ref!$A$1:$B$8,2,FALSE),"") -> 8 | J5: =IF(A5="","",IF(B5="",IF(TODAY()-A5>I5,"ATRASADA","EM ANDAMENTO"),IF(B5-A5>I5,"ATRASADA","NO PRAZO"))) -> NO PRAZO | K5: =Tabela2[[#This Row],[SLA Padrão]]-Tabela2[[#This Row],[SLA Atendimento]] -> 3 | M5: 137.8 | N5: 137.8 | O5: BRL | P5: =Tabela2[[#This Row],[Proposta Inicial]]-Tabela2[[#This Row],[Proposta Negociada]] -> 0 | Q5: =Tabela2[[#This Row],[Proposta Negociada]]/Tabela2[[#This Row],[Proposta Inicial]]-1 -> 0 | S5: RC10001658 | T5: 450000222 | W5: 213915 | X5: Sim | Y5: Sim
A6: 46202 | B6: 46204 | C6: =IF(OR(A6="",B6=""),"",B6-A6) -> 2 | D6: Michel Bernardes | E6: GEOLOGICAL EXPLORATION | F6: Comercial ArtPel | G6: Spot | H6: Material Normal | I6: =IFERROR(VLOOKUP(H6,SLA_Ref!$A$1:$B$8,2,FALSE),"") -> 8 | J6: =IF(A6="","",IF(B6="",IF(TODAY()-A6>I6,"ATRASADA","EM ANDAMENTO"),IF(B6-A6>I6,"ATRASADA","NO PRAZO"))) -> NO PRAZO | K6: =Tabela2[[#This Row],[SLA Padrão]]-Tabela2[[#This Row],[SLA Atendimento]] -> 6 | M6: 50 | N6: 50 | O6: BRL | P6: =Tabela2[[#This Row],[Proposta Inicial]]-Tabela2[[#This Row],[Proposta Negociada]] -> 0 | Q6: =Tabela2[[#This Row],[Proposta Negociada]]/Tabela2[[#This Row],[Proposta Inicial]]-1 -> 0 | S6: RC 10001655 | T6: 450000223 | W6: 54762 | X6: Sim | Y6: Sim
A7: 46202 | B7: 46204 | C7: =IF(OR(A7="",B7=""),"",B7-A7) -> 2 | D7: Amanda Salvi | E7: GEOLOGICAL EXPLORATION | F7: Sodre Miguel | G7: Spot | H7: Material Normal | I7: =IFERROR(VLOOKUP(H7,SLA_Ref!$A$1:$B$8,2,FALSE),"") -> 8 | J7: =IF(A7="","",IF(B7="",IF(TODAY()-A7>I7,"ATRASADA","EM ANDAMENTO"),IF(B7-A7>I7,"ATRASADA","NO PRAZO"))) -> NO PRAZO | K7: =Tabela2[[#This Row],[SLA Padrão]]-Tabela2[[#This Row],[SLA Atendimento]] -> 6 | M7: 18.98 | N7: 18.98 | O7: BRL | P7: =Tabela2[[#This Row],[Proposta Inicial]]-Tabela2[[#This Row],[Proposta Negociada]] -> 0 | Q7: =Tabela2[[#This Row],[Proposta Negociada]]/Tabela2[[#This Row],[Proposta Inicial]]-1 -> 0 | S7: RC 10001657 | T7: 450000224 | X7: Não | Y7: Sim
A8: 46203 | B8: 46205 | C8: =IF(OR(A8="",B8=""),"",B8-A8) -> 2 | D8: Michel Bernardes | E8: IT | F8: Ubiquiti Brazil | G8: Spot | H8: Material Urgente | I8: =IFERROR(VLOOKUP(H8,SLA_Ref!$A$1:$B$8,2,FALSE),"") -> 3 | J8: =IF(A8="","",IF(B8="",IF(TODAY()-A8>I8,"ATRASADA","EM ANDAMENTO"),IF(B8-A8>I8,"ATRASADA","NO PRAZO"))) -> NO PRAZO | K8: =Tabela2[[#This Row],[SLA Padrão]]-Tabela2[[#This Row],[SLA Atendimento]] -> 1 | M8: 3880 | N8: 3880 | O8: BRL | P8: =Tabela2[[#This Row],[Proposta Inicial]]-Tabela2[[#This Row],[Proposta Negociada]] -> 0 | Q8: =Tabela2[[#This Row],[Proposta Negociada]]/Tabela2[[#This Row],[Proposta Inicial]]-1 -> 0 | S8: RC 10001672 | T8: 450000226 | W8: 246857 | X8: Sim | Y8: Não
A9: 46204 | B9: 46205 | C9: =IF(OR(A9="",B9=""),"",B9-A9) -> 1 | D9: Michel Bernardes | E9: COMMUNITY RELATIONS | F9: MOVMED COMERCIO DE MOVEIS E PRODUTOS | G9: Spot | H9: Material Urgente | I9: =IFERROR(VLOOKUP(H9,SLA_Ref!$A$1:$B$8,2,FALSE),"") -> 3 | J9: =IF(A9="","",IF(B9="",IF(TODAY()-A9>I9,"ATRASADA","EM ANDAMENTO"),IF(B9-A9>I9,"ATRASADA","NO PRAZO"))) -> NO PRAZO | K9: =Tabela2[[#This Row],[SLA Padrão]]-Tabela2[[#This Row],[SLA Atendimento]] -> 2 | M9: 25591 | N9: 23800 | O9: BRL | P9: =Tabela2[[#This Row],[Proposta Inicial]]-Tabela2[[#This Row],[Proposta Negociada]] -> 1791 | Q9: =Tabela2[[#This Row],[Proposta Negociada]]/Tabela2[[#This Row],[Proposta Inicial]]-1 -> -0.069985542 | R9: Cost Avoidance | S9: RC 10001633 | T9: 450000227 | X9: Não | Y9: Não
A10: 46202 | B10: 46205 | C10: =IF(OR(A10="",B10=""),"",B10-A10) -> 3 | D10: Michel Bernardes | E10: GEOLOGICAL EXPLORATION | F10: Toque de Cor | G10: Spot | H10: Material Normal | I10: =IFERROR(VLOOKUP(H10,SLA_Ref!$A$1:$B$8,2,FALSE),"") -> 8 | J10: =IF(A10="","",IF(B10="",IF(TODAY()-A10>I10,"ATRASADA","EM ANDAMENTO"),IF(B10-A10>I10,"ATRASADA","NO PRAZO"))) -> NO PRAZO | K10: =Tabela2[[#This Row],[SLA Padrão]]-Tabela2[[#This Row],[SLA Atendimento]] -> 5 | M10: 63.99 | N10: 63.99 | O10: BRL | P10: =Tabela2[[#This Row],[Proposta Inicial]]-Tabela2[[#This Row],[Proposta Negociada]] -> 0 | Q10: =Tabela2[[#This Row],[Proposta Negociada]]/Tabela2[[#This Row],[Proposta Inicial]]-1 -> 0 | S10: RC 10001659 | T10: 450000228 | W10: 1912 | X10: Sim | Y10: Sim
A11: 46189 | B11: 46205 | C11: =IF(OR(A11="",B11=""),"",B11-A11) -> 16 | D11: Michel Bernardes | E11: ENVIRONMENT | F11: Sievert Laboratórios | G11: Spot | H11: Contrato Contínuo Simples | I11: 30 | J11: =IF(A11="","",IF(B11="",IF(TODAY()-A11>I11,"ATRASADA","EM ANDAMENTO"),IF(B11-A11>I11,"ATRASADA","NO PRAZO"))) -> NO PRAZO | K11: =Tabela2[[#This Row],[SLA Padrão]]-Tabela2[[#This Row],[SLA Atendimento]] -> 14 | M11: 120000 | N11: 108000 | O11: BRL | P11: =Tabela2[[#This Row],[Proposta Inicial]]-Tabela2[[#This Row],[Proposta Negociada]] -> 12000 | Q11: =Tabela2[[#This Row],[Proposta Negociada]]/Tabela2[[#This Row],[Proposta Inicial]]-1 -> -0.1 | R11: Cost Avoidance | S11: Programa de proteção radiológica CPTR | T11: 450000229 | W11: 87 | X11: Sim | Y11: Não
A12: 46203 | B12: 46206 | C12: =IF(OR(A12="",B12=""),"",B12-A12) -> 3 | D12: Michel Bernardes | E12: COMMUNITY RELATIONS | F12: PP Caponi | G12: Spot | H12: Material Normal | I12: =IFERROR(VLOOKUP(H12,SLA_Ref!$A$1:$B$8,2,FALSE),"") -> 8 | J12: =IF(A12="","",IF(B12="",IF(TODAY()-A12>I12,"ATRASADA","EM ANDAMENTO"),IF(B12-A12>I12,"ATRASADA","NO PRAZO"))) -> NO PRAZO | K12: =Tabela2[[#This Row],[SLA Padrão]]-Tabela2[[#This Row],[SLA Atendimento]] -> 5 | M12: 110 | N12: 110 | O12: BRL | P12: =Tabela2[[#This Row],[Proposta Inicial]]-Tabela2[[#This Row],[Proposta Negociada]] -> 0 | Q12: =Tabela2[[#This Row],[Proposta Negociada]]/Tabela2[[#This Row],[Proposta Inicial]]-1 -> 0 | S12: RC 10001667 - Cristal | T12: 450000231 | W12: 6612 | X12: Sim | Y12: Sim
A13: 46202 | B13: 46206 | C13: =IF(OR(A13="",B13=""),"",B13-A13) -> 4 | D13: Amanda Salvi | E13: SUSTAINABILITY | F13: Marcelo Batista | G13: Spot | H13: Serviço Normal | I13: =IFERROR(VLOOKUP(H13,SLA_Ref!$A$1:$B$8,2,FALSE),"") -> 15 | J13: =IF(A13="","",IF(B13="",IF(TODAY()-A13>I13,"ATRASADA","EM ANDAMENTO"),IF(B13-A13>I13,"ATRASADA","NO PRAZO"))) -> NO PRAZO | K13: =Tabela2[[#This Row],[SLA Padrão]]-Tabela2[[#This Row],[SLA Atendimento]] -> 11 | M13: 900 | N13: 800 | O13: BRL | P13: =Tabela2[[#This Row],[Proposta Inicial]]-Tabela2[[#This Row],[Proposta Negociada]] -> 100 | Q13: =Tabela2[[#This Row],[Proposta Negociada]]/Tabela2[[#This Row],[Proposta Inicial]]-1 -> -0.11111111 | R13: Cost Avoidance | S13: RC 10001564 | T13: 450000232 | X13: Não | Y13: Sim
A14: 46205 | B14: 46206 | C14: =IF(OR(A14="",B14=""),"",B14-A14) -> 1 | D14: Amanda Salvi | E14: CPTR | F14: Base Quimica SA | G14: Spot | H14: Material Urgente | I14: =IFERROR(VLOOKUP(H14,SLA_Ref!$A$1:$B$8,2,FALSE),"") -> 3 | J14: =IF(A14="","",IF(B14="",IF(TODAY()-A14>I14,"ATRASADA","EM ANDAMENTO"),IF(B14-A14>I14,"ATRASADA","NO PRAZO"))) -> NO PRAZO | K14: =Tabela2[[#This Row],[SLA Padrão]]-Tabela2[[#This Row],[SLA Atendimento]] -> 2 | M14: 8137.5 | N14: 8137.5 | O14: BRL | P14: =Tabela2[[#This Row],[Proposta Inicial]]-Tabela2[[#This Row],[Proposta Negociada]] -> 0 | Q14: =Tabela2[[#This Row],[Proposta Negociada]]/Tabela2[[#This Row],[Proposta Inicial]]-1 -> 0 | S14: RC 10001684 - Sulfato de Amônio (AmSul) para operação – CPTR | T14: 450000233 | W14: 564328 | X14: Sim | Y14: Não
A15: 46204 | B15: 46209 | C15: =IF(OR(A15="",B15=""),"",B15-A15) -> 5 | D15: Michel Bernardes | E15: HUMAN RESOURCES | F15: A C N PALMILHAS E BRINDES LTDA | G15: Spot | H15: Serviço Normal | I15: =IFERROR(VLOOKUP(H15,SLA_Ref!$A$1:$B$8,2,FALSE),"") -> 15 | J15: =IF(A15="","",IF(B15="",IF(TODAY()-A15>I15,"ATRASADA","EM ANDAMENTO"),IF(B15-A15>I15,"ATRASADA","NO PRAZO"))) -> NO PRAZO | K15: =Tabela2[[#This Row],[SLA Padrão]]-Tabela2[[#This Row],[SLA Atendimento]] -> 10 | M15: =14.95*100 -> 1495 | N15: =13.95*100 -> 1395 | O15: BRL | P15: =Tabela2[[#This Row],[Proposta Inicial]]-Tabela2[[#This Row],[Proposta Negociada]] -> 100 | Q15: =Tabela2[[#This Row],[Proposta Negociada]]/Tabela2[[#This Row],[Proposta Inicial]]-1 -> -0.066889632 | R15: Cost Avoidance | S15: RC 10001681 - MOUSE PAD ERGONÔMICO PERSONALIZADO Viridis | T15: 450000234 | W15: 23103 | X15: Sim | Y15: Não
A16: 46203 | B16: 46209 | C16: =IF(OR(A16="",B16=""),"",B16-A16) -> 6 | D16: Michel Bernardes | E16: COMMUNITY RELATIONS | F16: Cristais São Marcos | G16: Spot | H16: Serviço Normal | I16: =IFERROR(VLOOKUP(H16,SLA_Ref!$A$1:$B$8,2,FALSE),"") -> 15 | J16: =IF(A16="","",IF(B16="",IF(TODAY()-A16>I16,"ATRASADA","EM ANDAMENTO"),IF(B16-A16>I16,"ATRASADA","NO PRAZO"))) -> NO PRAZO | K16: =Tabela2[[#This Row],[SLA Padrão]]-Tabela2[[#This Row],[SLA Atendimento]] -> 9 | M16: 2051.8 | N16: 2051.8 | O16: BRL | P16: =Tabela2[[#This Row],[Proposta Inicial]]-Tabela2[[#This Row],[Proposta Negociada]] -> 0 | Q16: =Tabela2[[#This Row],[Proposta Negociada]]/Tabela2[[#This Row],[Proposta Inicial]]-1 -> 0 | S16: RC 10001667 - Cristal | T16: 450000235 | W16: 28281 | X16: Sim | Y16: Sim
A17: 46201 | B17: 46204 | C17: =IF(OR(A17="",B17=""),"",B17-A17) -> 3 | D17: Amanda Salvi | E17: ADMINISTRATIVE | F17: Tec Print Suprimentos e Assistencia | G17: Spot | H17: Serviço Normal | I17: =IFERROR(VLOOKUP(H17,SLA_Ref!$A$1:$B$8,2,FALSE),"") -> 15 | J17: =IF(A17="","",IF(B17="",IF(TODAY()-A17>I17,"ATRASADA","EM ANDAMENTO"),IF(B17-A17>I17,"ATRASADA","NO PRAZO"))) -> NO PRAZO | K17: =Tabela2[[#This Row],[SLA Padrão]]-Tabela2[[#This Row],[SLA Atendimento]] -> 12 | M17: 76.62 | N17: 76.62 | O17: BRL | P17: =Tabela2[[#This Row],[Proposta Inicial]]-Tabela2[[#This Row],[Proposta Negociada]] -> 0 | Q17: =Tabela2[[#This Row],[Proposta Negociada]]/Tabela2[[#This Row],[Proposta Inicial]]-1 -> 0 | S17: RC 10001645 | T17: 450000236 | X17: Não | Y17: Não
A18: 46192 | B18: 46206 | C18: =IF(OR(A18="",B18=""),"",B18-A18) -> 14 | D18: Amanda Salvi | E18: ADMINISTRATIVE | F18: Ebazar.com.br Utilidades Ltda | G18: Spot | H18: Serviço Normal | I18: =IFERROR(VLOOKUP(H18,SLA_Ref!$A$1:$B$8,2,FALSE),"") -> 15 | J18: =IF(A18="","",IF(B18="",IF(TODAY()-A18>I18,"ATRASADA","EM ANDAMENTO"),IF(B18-A18>I18,"ATRASADA","NO PRAZO"))) -> NO PRAZO | K18: =Tabela2[[#This Row],[SLA Padrão]]-Tabela2[[#This Row],[SLA Atendimento]] -> 1 | M18: 80 | N18: 80 | O18: BRL | P18: =Tabela2[[#This Row],[Proposta Inicial]]-Tabela2[[#This Row],[Proposta Negociada]] -> 0 | Q18: =Tabela2[[#This Row],[Proposta Negociada]]/Tabela2[[#This Row],[Proposta Inicial]]-1 -> 0 | S18: RC 10001624 | T18: 450000238 | X18: Não | Y18: Não
A19: 46205 | B19: 46199 | C19: =IF(OR(A19="",B19=""),"",B19-A19) -> -6 | D19: Júlia Guidorizzi | E19: CPTR | F19: WMF Brazil Ltda | G19: Spot | H19: Serviço Urgente | I19: =IFERROR(VLOOKUP(H19,SLA_Ref!$A$1:$B$8,2,FALSE),"") -> 5 | J19: =IF(A19="","",IF(B19="",IF(TODAY()-A19>I19,"ATRASADA","EM ANDAMENTO"),IF(B19-A19>I19,"ATRASADA","NO PRAZO"))) -> NO PRAZO | K19: =Tabela2[[#This Row],[SLA Padrão]]-Tabela2[[#This Row],[SLA Atendimento]] -> 11 | M19: 1534.96 | N19: 1534.96 | O19: BRL | P19: =Tabela2[[#This Row],[Proposta Inicial]]-Tabela2[[#This Row],[Proposta Negociada]] -> 0 | Q19: =Tabela2[[#This Row],[Proposta Negociada]]/Tabela2[[#This Row],[Proposta Inicial]]-1 -> 0 | S19: RC 10001664 - REGULARIZAÇÃO - Envio de amostra de MREC para Solvay - CPTR | T19: 450000239 | W19: 02449-0726 | X19: Sim | Y19: Não
A20: 46206 | B20: 46209 | C20: =IF(OR(A20="",B20=""),"",B20-A20) -> 3 | D20: Michel Bernardes | E20: ENVIRONMENT | F20: EHS Treinamentos | G20: Spot | H20: Serviço Normal | I20: =IFERROR(VLOOKUP(H20,SLA_Ref!$A$1:$B$8,2,FALSE),"") -> 15 | J20: =IF(A20="","",IF(B20="",IF(TODAY()-A20>I20,"ATRASADA","EM ANDAMENTO"),IF(B20-A20>I20,"ATRASADA","NO PRAZO"))) -> NO PRAZO | K20: =Tabela2[[#This Row],[SLA Padrão]]-Tabela2[[#This Row],[SLA Atendimento]] -> 12 | M20: 3000 | N20: 2500 | O20: BRL | P20: =Tabela2[[#This Row],[Proposta Inicial]]-Tabela2[[#This Row],[Proposta Negociada]] -> 500 | Q20: =Tabela2[[#This Row],[Proposta Negociada]]/Tabela2[[#This Row],[Proposta Inicial]]-1 -> -0.16666667 | R20: Cost Avoidance | S20: RC 10001699 - Monitoramento de Ruído - CPTR | T20: 450000240 | X20: Não | Y20: Sim
A21: 46206 | B21: 46209 | C21: =IF(OR(A21="",B21=""),"",B21-A21) -> 3 | D21: Amanda Salvi | E21: GEOLOGICAL EXPLORATION | F21: Casa Sao Juliao Comercio de Tintas Ltda | G21: Spot | H21: Material Urgente | I21: =IFERROR(VLOOKUP(H21,SLA_Ref!$A$1:$B$8,2,FALSE),"") -> 3 | J21: =IF(A21="","",IF(B21="",IF(TODAY()-A21>I21,"ATRASADA","EM ANDAMENTO"),IF(B21-A21>I21,"ATRASADA","NO PRAZO"))) -> NO PRAZO | K21: =Tabela2[[#This Row],[SLA Padrão]]-Tabela2[[#This Row],[SLA Atendimento]] -> 0 | M21: 145 | N21: 130 | O21: BRL | P21: =Tabela2[[#This Row],[Proposta Inicial]]-Tabela2[[#This Row],[Proposta Negociada]] -> 15 | Q21: =Tabela2[[#This Row],[Proposta Negociada]]/Tabela2[[#This Row],[Proposta Inicial]]-1 -> -0.10344828 | R21: Cost Avoidance | S21: RC 10001704 | T21: 450000241 | X21: Sim | Y21: Sim
A22: 46213 | B22: 46210 | C22: =IF(OR(A22="",B22=""),"",B22-A22) -> -3 | D22: Amanda Salvi | E22: CPTR | F22: Eletrochoque Comercial Eletrica LTda | G22: Spot | H22: Regularização | I22: =IFERROR(VLOOKUP(H22,SLA_Ref!$A$1:$B$8,2,FALSE),"") -> 30 | J22: =IF(A22="","",IF(B22="",IF(TODAY()-A22>I22,"ATRASADA","EM ANDAMENTO"),IF(B22-A22>I22,"ATRASADA","NO PRAZO"))) -> NO PRAZO | K22: =Tabela2[[#This Row],[SLA Padrão]]-Tabela2[[#This Row],[SLA Atendimento]] -> 33 | M22: 197.9 | N22: 197.9 | O22: BRL | P22: =Tabela2[[#This Row],[Proposta Inicial]]-Tabela2[[#This Row],[Proposta Negociada]] -> 0 | Q22: =Tabela2[[#This Row],[Proposta Negociada]]/Tabela2[[#This Row],[Proposta Inicial]]-1 -> 0 | S22: Regularização - Instalação do Tanque e Agitador 3110TH001 | T22: 450000243 | X22: Sim | Y22: Sim
A23: 46209 | B23: 46206 | C23: =IF(OR(A23="",B23=""),"",B23-A23) -> -3 | D23: Amanda Salvi | E23: ADMINISTRATIVE | F23: Disk Limpeza Total Ltda | G23: Spot | H23: Regularização | I23: =IFERROR(VLOOKUP(H23,SLA_Ref!$A$1:$B$8,2,FALSE),"") -> 30 | J23: =IF(A23="","",IF(B23="",IF(TODAY()-A23>I23,"ATRASADA","EM ANDAMENTO"),IF(B23-A23>I23,"ATRASADA","NO PRAZO"))) -> NO PRAZO | K23: =Tabela2[[#This Row],[SLA Padrão]]-Tabela2[[#This Row],[SLA Atendimento]] -> 33 | M23: 448.01 | N23: 448.01 | O23: BRL | P23: =Tabela2[[#This Row],[Proposta Inicial]]-Tabela2[[#This Row],[Proposta Negociada]] -> 0 | Q23: =Tabela2[[#This Row],[Proposta Negociada]]/Tabela2[[#This Row],[Proposta Inicial]]-1 -> 0 | S23: RC 10001693 - Itens de Limpeza Argentina Mall | T23: 450000244 | X23: Sim | Y23: Sim
A24: 46209 | B24: 46210 | C24: =IF(OR(A24="",B24=""),"",B24-A24) -> 1 | D24: Michel Bernardes | E24: HSE | F24: 1000 Marcas | G24: Spot | H24: Material Normal | I24: =IFERROR(VLOOKUP(H24,SLA_Ref!$A$1:$B$8,2,FALSE),"") -> 8 | J24: =IF(A24="","",IF(B24="",IF(TODAY()-A24>I24,"ATRASADA","EM ANDAMENTO"),IF(B24-A24>I24,"ATRASADA","NO PRAZO"))) -> NO PRAZO | K24: =Tabela2[[#This Row],[SLA Padrão]]-Tabela2[[#This Row],[SLA Atendimento]] -> 7 | M24: 3202.8 | N24: 3042.72 | O24: BRL | P24: =Tabela2[[#This Row],[Proposta Inicial]]-Tabela2[[#This Row],[Proposta Negociada]] -> 160.08 | Q24: =Tabela2[[#This Row],[Proposta Negociada]]/Tabela2[[#This Row],[Proposta Inicial]]-1 -> -0.049981266 | R24: Cost Avoidance | S24: RC 10001703 - Botinas de segurança com sistema anti-torção - Marluvas (CA nº 34550) | T24: 450000245 | W24: 735221 | X24: Sim | Y24: Não
A25: 46210 | B25: 46210 | C25: =IF(OR(A25="",B25=""),"",B25-A25) -> 0 | D25: Michel Bernardes | E25: PURCHASING | F25: Poços Print | G25: Spot | H25: Material Normal | I25: =IFERROR(VLOOKUP(H25,SLA_Ref!$A$1:$B$8,2,FALSE),"") -> 8 | J25: =IF(A25="","",IF(B25="",IF(TODAY()-A25>I25,"ATRASADA","EM ANDAMENTO"),IF(B25-A25>I25,"ATRASADA","NO PRAZO"))) -> NO PRAZO | K25: =Tabela2[[#This Row],[SLA Padrão]]-Tabela2[[#This Row],[SLA Atendimento]] -> 8 | M25: 400 | N25: 400 | O25: BRL | P25: =Tabela2[[#This Row],[Proposta Inicial]]-Tabela2[[#This Row],[Proposta Negociada]] -> 0 | Q25: =Tabela2[[#This Row],[Proposta Negociada]]/Tabela2[[#This Row],[Proposta Inicial]]-1 -> 0 | S25: RC 10001698 - Tintas Epson 544 para Impressora EcoTank | T25: 450000246 | W25: 1178 | X25: Sim | Y25: Sim
A26: 46205 | B26: 46211 | C26: =IF(OR(A26="",B26=""),"",B26-A26) -> 6 | D26: Michel Bernardes | E26: CPTR | F26: alpha Abras | G26: Spot | H26: Material Normal | I26: =IFERROR(VLOOKUP(H26,SLA_Ref!$A$1:$B$8,2,FALSE),"") -> 8 | J26: =IF(A26="","",IF(B26="",IF(TODAY()-A26>I26,"ATRASADA","EM ANDAMENTO"),IF(B26-A26>I26,"ATRASADA","NO PRAZO"))) -> NO PRAZO | K26: =Tabela2[[#This Row],[SLA Padrão]]-Tabela2[[#This Row],[SLA Atendimento]] -> 2 | M26: 494.1 | N26: 494.1 | O26: BRL | P26: =Tabela2[[#This Row],[Proposta Inicial]]-Tabela2[[#This Row],[Proposta Negociada]] -> 0 | Q26: =Tabela2[[#This Row],[Proposta Negociada]]/Tabela2[[#This Row],[Proposta Inicial]]-1 -> 0 | S26: RC 10001692 - Abraçadeiras de nylon – CPTR | T26: 450000248 | W26: 214453 | X26: Sim | Y26: Sim
A27: 46188 | B27: 46206 | C27: =IF(OR(A27="",B27=""),"",B27-A27) -> 18 | D27: Amanda Salvi | E27: ADMINISTRATIVE | F27: Deiseane Alves | G27: Spot | H27: Material Normal | I27: =IFERROR(VLOOKUP(H27,SLA_Ref!$A$1:$B$8,2,FALSE),"") -> 8 | J27: =IF(A27="","",IF(B27="",IF(TODAY()-A27>I27,"ATRASADA","EM ANDAMENTO"),IF(B27-A27>I27,"ATRASADA","NO PRAZO"))) -> ATRASADA | K27: =Tabela2[[#This Row],[SLA Padrão]]-Tabela2[[#This Row],[SLA Atendimento]] -> -10 | M27: 1450 | N27: 1000 | O27: BRL | P27: =Tabela2[[#This Row],[Proposta Inicial]]-Tabela2[[#This Row],[Proposta Negociada]] -> 450 | Q27: =Tabela2[[#This Row],[Proposta Negociada]]/Tabela2[[#This Row],[Proposta Inicial]]-1 -> -0.31034483 | R27: Cost Avoidance | S27: RC 10001593 - Gaveteiro com Chave para Compras, Facilities e Frota | T27: 450000250 | X27: Não | Y27: Sim
A28: 46204 | B28: 46206 | C28: =IF(OR(A28="",B28=""),"",B28-A28) -> 2 | D28: Michel Bernardes | E28: COMMUNITY RELATIONS | F28: Borges Comecio e Equipamentos | G28: Spot | H28: Material Normal | I28: =IFERROR(VLOOKUP(H28,SLA_Ref!$A$1:$B$8,2,FALSE),"") -> 8 | J28: =IF(A28="","",IF(B28="",IF(TODAY()-A28>I28,"ATRASADA","EM ANDAMENTO"),IF(B28-A28>I28,"ATRASADA","NO PRAZO"))) -> NO PRAZO | K28: =Tabela2[[#This Row],[SLA Padrão]]-Tabela2[[#This Row],[SLA Atendimento]] -> 6 | M28: 692 | N28: 692 | O28: BRL | P28: =Tabela2[[#This Row],[Proposta Inicial]]-Tabela2[[#This Row],[Proposta Negociada]] -> 0 | Q28: =Tabela2[[#This Row],[Proposta Negociada]]/Tabela2[[#This Row],[Proposta Inicial]]-1 -> 0 | S28: RC 10001677 - Tela para projeção CPTR | T28: 450000251 | W28: 1408253 | X28: Sim | Y28: Não
A29: 46202 | B29: 46205 | C29: =IF(OR(A29="",B29=""),"",B29-A29) -> 3 | D29: Michel Bernardes | E29: GEOLOGICAL EXPLORATION | F29: Alpha Brasil Goiania | G29: Spot | H29: Material Normal | I29: =IFERROR(VLOOKUP(H29,SLA_Ref!$A$1:$B$8,2,FALSE),"") -> 8 | J29: =IF(A29="","",IF(B29="",IF(TODAY()-A29>I29,"ATRASADA","EM ANDAMENTO"),IF(B29-A29>I29,"ATRASADA","NO PRAZO"))) -> NO PRAZO | K29: =Tabela2[[#This Row],[SLA Padrão]]-Tabela2[[#This Row],[SLA Atendimento]] -> 5 | M29: 170.3 | N29: 170.3 | O29: BRL | P29: =Tabela2[[#This Row],[Proposta Inicial]]-Tabela2[[#This Row],[Proposta Negociada]] -> 0 | Q29: =Tabela2[[#This Row],[Proposta Negociada]]/Tabela2[[#This Row],[Proposta Inicial]]-1 -> 0 | S29: RC 10001656 - Pisante traseiro direito (TXP8I65) | T29: 450000252 | W29: 3487 | X29: Sim | Y29: Não
A30: 46202 | B30: 46205 | C30: =IF(OR(A30="",B30=""),"",B30-A30) -> 3 | D30: Michel Bernardes | E30: GEOLOGICAL EXPLORATION | F30: truck Shop Comercio LTDA | G30: Spot | H30: Material Normal | I30: =IFERROR(VLOOKUP(H30,SLA_Ref!$A$1:$B$8,2,FALSE),"") -> 8 | J30: =IF(A30="","",IF(B30="",IF(TODAY()-A30>I30,"ATRASADA","EM ANDAMENTO"),IF(B30-A30>I30,"ATRASADA","NO PRAZO"))) -> NO PRAZO | K30: =Tabela2[[#This Row],[SLA Padrão]]-Tabela2[[#This Row],[SLA Atendimento]] -> 5 | M30: 58.38 | N30: 58.38 | O30: BRL | P30: =Tabela2[[#This Row],[Proposta Inicial]]-Tabela2[[#This Row],[Proposta Negociada]] -> 0 | Q30: =Tabela2[[#This Row],[Proposta Negociada]]/Tabela2[[#This Row],[Proposta Inicial]]-1 -> 0 | S30: RC 10001647 - Calços para caminhonete | T30: 450000253 | W30: 18005 | X30: Sim | Y30: Não
A31: 46205 | B31: 46211 | C31: =IF(OR(A31="",B31=""),"",B31-A31) -> 6 | D31: Michel Bernardes | E31: CPTR | F31: A.M Marques Produtos para Laboratórios | G31: Spot | H31: Material Normal | I31: =IFERROR(VLOOKUP(H31,SLA_Ref!$A$1:$B$8,2,FALSE),"") -> 8 | J31: =IF(A31="","",IF(B31="",IF(TODAY()-A31>I31,"ATRASADA","EM ANDAMENTO"),IF(B31-A31>I31,"ATRASADA","NO PRAZO"))) -> NO PRAZO | K31: =Tabela2[[#This Row],[SLA Padrão]]-Tabela2[[#This Row],[SLA Atendimento]] -> 2 | M31: 30 | N31: 30 | O31: BRL | P31: =Tabela2[[#This Row],[Proposta Inicial]]-Tabela2[[#This Row],[Proposta Negociada]] -> 0 | Q31: =Tabela2[[#This Row],[Proposta Negociada]]/Tabela2[[#This Row],[Proposta Inicial]]-1 -> 0 | S31: RC 10001649 - Papel filtro para kitassato | T31: 450000254 | W31: 323297 | X31: Sim | Y31: Não
A32: 46206 | B32: 46216 | C32: =IF(OR(A32="",B32=""),"",B32-A32) -> 10 | D32: Michel Bernardes | E32: CPTR | F32: Watson-Marlow | G32: Spot | H32: Material Normal | I32: =IFERROR(VLOOKUP(H32,SLA_Ref!$A$1:$B$8,2,FALSE),"") -> 8 | J32: =IF(A32="","",IF(B32="",IF(TODAY()-A32>I32,"ATRASADA","EM ANDAMENTO"),IF(B32-A32>I32,"ATRASADA","NO PRAZO"))) -> ATRASADA | K32: =Tabela2[[#This Row],[SLA Padrão]]-Tabela2[[#This Row],[SLA Atendimento]] -> -2 | M32: =31541.559+2000 -> 33541.559 | N32: 30039.58 | O32: BRL | P32: =Tabela2[[#This Row],[Proposta Inicial]]-Tabela2[[#This Row],[Proposta Negociada]] -> 3501.979 | Q32: =Tabela2[[#This Row],[Proposta Negociada]]/Tabela2[[#This Row],[Proposta Inicial]]-1 -> -0.10440716 | R32: Cost Avoidance | S32: Melhoria Processo: Bomba recirculação espessadores | T32: 450000255 | X32: Não | Y32: Não
A33: 46211 | B33: 46212 | C33: =IF(OR(A33="",B33=""),"",B33-A33) -> 1 | D33: Michel Bernardes | E33: HUMAN RESOURCES | F33: A.S.D Atividades Fisicas e Fitnes | G33: Spot | H33: Material Normal | I33: =IFERROR(VLOOKUP(H33,SLA_Ref!$A$1:$B$8,2,FALSE),"") -> 8 | J33: =IF(A33="","",IF(B33="",IF(TODAY()-A33>I33,"ATRASADA","EM ANDAMENTO"),IF(B33-A33>I33,"ATRASADA","NO PRAZO"))) -> NO PRAZO | K33: =Tabela2[[#This Row],[SLA Padrão]]-Tabela2[[#This Row],[SLA Atendimento]] -> 7 | M33: 499 | N33: 499 | O33: BRL | P33: =Tabela2[[#This Row],[Proposta Inicial]]-Tabela2[[#This Row],[Proposta Negociada]] -> 0 | Q33: =Tabela2[[#This Row],[Proposta Negociada]]/Tabela2[[#This Row],[Proposta Inicial]]-1 -> 0 | S33: RC 10001652 - Podium de Premiação (para uso no Viridis Fitness Day) | T33: 450000256 | W33: 66922 | X33: Sim | Y33: Não
A34: 46210 | B34: 46211 | C34: =IF(OR(A34="",B34=""),"",B34-A34) -> 1 | D34: Michel Bernardes | E34: HUMAN RESOURCES | F34: 67.607.454 FELIPE DETOFOLI VIEIRA | G34: Spot | H34: Material Urgente | I34: =IFERROR(VLOOKUP(H34,SLA_Ref!$A$1:$B$8,2,FALSE),"") -> 3 | J34: =IF(A34="","",IF(B34="",IF(TODAY()-A34>I34,"ATRASADA","EM ANDAMENTO"),IF(B34-A34>I34,"ATRASADA","NO PRAZO"))) -> NO PRAZO | K34: =Tabela2[[#This Row],[SLA Padrão]]-Tabela2[[#This Row],[SLA Atendimento]] -> 2 | M34: =100*49 -> 4900 | N34: 4000 | O34: BRL | P34: =Tabela2[[#This Row],[Proposta Inicial]]-Tabela2[[#This Row],[Proposta Negociada]] -> 900 | Q34: =Tabela2[[#This Row],[Proposta Negociada]]/Tabela2[[#This Row],[Proposta Inicial]]-1 -> -0.18367347 | R34: Cost Avoidance | S34: RC 10001665 - Porta-retrato personalizado inauguração Programa RARO | T34: 450000257 | W34: 32 | X34: Sim | Y34: Não
A35: 46210 | B35: 46213 | C35: =IF(OR(A35="",B35=""),"",B35-A35) -> 3 | D35: Michel Bernardes | E35: IT | F35: BluePex | G35: Contrato | H35: Serviço Normal | I35: =IFERROR(VLOOKUP(H35,SLA_Ref!$A$1:$B$8,2,FALSE),"") -> 15 | J35: =IF(A35="","",IF(B35="",IF(TODAY()-A35>I35,"ATRASADA","EM ANDAMENTO"),IF(B35-A35>I35,"ATRASADA","NO PRAZO"))) -> NO PRAZO | K35: =Tabela2[[#This Row],[SLA Padrão]]-Tabela2[[#This Row],[SLA Atendimento]] -> 12 | M35: 16020 | N35: 9924.96 | O35: BRL | P35: =Tabela2[[#This Row],[Proposta Inicial]]-Tabela2[[#This Row],[Proposta Negociada]] -> 6095.04 | Q35: =Tabela2[[#This Row],[Proposta Negociada]]/Tabela2[[#This Row],[Proposta Inicial]]-1 -> -0.38046442 | R35: Cost Avoidance | S35: RC 10001669 - Firewall | T35: 450000258 | X35: Não | Y35: Não
A36: 46199 | B36: 46209 | C36: =IF(OR(A36="",B36=""),"",B36-A36) -> 10 | D36: Amanda Salvi | E36: CAPEX | F36: Sherwin Williams do Brasil Industrial e Comercio Ltda | G36: Spot | H36: Material Normal | I36: =IFERROR(VLOOKUP(H36,SLA_Ref!$A$1:$B$8,2,FALSE),"") -> 8 | J36: =IF(A36="","",IF(B36="",IF(TODAY()-A36>I36,"ATRASADA","EM ANDAMENTO"),IF(B36-A36>I36,"ATRASADA","NO PRAZO"))) -> ATRASADA | K36: =Tabela2[[#This Row],[SLA Padrão]]-Tabela2[[#This Row],[SLA Atendimento]] -> -2 | M36: 2397.46 | N36: 2397.46 | O36: BRL | P36: =Tabela2[[#This Row],[Proposta Inicial]]-Tabela2[[#This Row],[Proposta Negociada]] -> 0 | Q36: =Tabela2[[#This Row],[Proposta Negociada]]/Tabela2[[#This Row],[Proposta Inicial]]-1 -> 0 | S36: Tintas para pintura do caminho seguro do CPTR | T36: 450000259 | X36: Não | Y36: Sim
A37: 46212 | B37: 46212 | C37: =IF(OR(A37="",B37=""),"",B37-A37) -> 0 | D37: Amanda Salvi | E37: ADMINISTRATIVE | F37: Esvatech e Cia Comercio e Representacoes | G37: Spot | H37: Material Normal | I37: =IFERROR(VLOOKUP(H37,SLA_Ref!$A$1:$B$8,2,FALSE),"") -> 8 | J37: =IF(A37="","",IF(B37="",IF(TODAY()-A37>I37,"ATRASADA","EM ANDAMENTO"),IF(B37-A37>I37,"ATRASADA","NO PRAZO"))) -> NO PRAZO | K37: =Tabela2[[#This Row],[SLA Padrão]]-Tabela2[[#This Row],[SLA Atendimento]] -> 8 | M37: 127 | N37: 127 | O37: BRL | P37: =Tabela2[[#This Row],[Proposta Inicial]]-Tabela2[[#This Row],[Proposta Negociada]] -> 0 | Q37: =Tabela2[[#This Row],[Proposta Negociada]]/Tabela2[[#This Row],[Proposta Inicial]]-1 -> 0 | S37: RC 10001722 - Fruteira Refeitório Argentina Mall | T37: 450000260 | X37: Sim | Y37: Não
A38: 46212 | B38: 46213 | C38: =IF(OR(A38="",B38=""),"",B38-A38) -> 1 | D38: Michel Bernardes | E38: CPTR | F38: Máximo Laboratório | G38: Spot | H38: Material Normal | I38: =IFERROR(VLOOKUP(H38,SLA_Ref!$A$1:$B$8,2,FALSE),"") -> 8 | J38: =IF(A38="","",IF(B38="",IF(TODAY()-A38>I38,"ATRASADA","EM ANDAMENTO"),IF(B38-A38>I38,"ATRASADA","NO PRAZO"))) -> NO PRAZO | K38: =Tabela2[[#This Row],[SLA Padrão]]-Tabela2[[#This Row],[SLA Atendimento]] -> 7 | M38: 899 | N38: 399 | O38: BRL | P38: =Tabela2[[#This Row],[Proposta Inicial]]-Tabela2[[#This Row],[Proposta Negociada]] -> 500 | Q38: =Tabela2[[#This Row],[Proposta Negociada]]/Tabela2[[#This Row],[Proposta Inicial]]-1 -> -0.55617353 | R38: Cost Avoidance | S38: RC 10001723 - Tubos Falcon 15 mL para Laboratório – CPTR | T38: 450000261 | W38: 76868 | X38: sim | Y38: Não
A39: 46212 | B39: 46214 | C39: =IF(OR(A39="",B39=""),"",B39-A39) -> 2 | D39: Michel Bernardes | E39: COMMUNITY RELATIONS | F39: Fabiana Brinquedos | G39: Spot | H39: Serviço Urgente | I39: =IFERROR(VLOOKUP(H39,SLA_Ref!$A$1:$B$8,2,FALSE),"") -> 5 | J39: =IF(A39="","",IF(B39="",IF(TODAY()-A39>I39,"ATRASADA","EM ANDAMENTO"),IF(B39-A39>I39,"ATRASADA","NO PRAZO"))) -> NO PRAZO | K39: =Tabela2[[#This Row],[SLA Padrão]]-Tabela2[[#This Row],[SLA Atendimento]] -> 3 | M39: 13000 | N39: 12000 | O39: BRL | P39: =Tabela2[[#This Row],[Proposta Inicial]]-Tabela2[[#This Row],[Proposta Negociada]] -> 1000 | Q39: =Tabela2[[#This Row],[Proposta Negociada]]/Tabela2[[#This Row],[Proposta Inicial]]-1 -> -0.076923077 | R39: Cost Avoidance | S39: RC 10001720 - Aluguel de Brinquedos Infláveis, pipoca e algodão doce para o Festival de Inverno | T39: 450000262 | W39: 236 | X39: Sim | Y39: Sim
A40: 46213 | B40: 46216 | C40: =IF(OR(A40="",B40=""),"",B40-A40) -> 3 | D40: Michel Bernardes | E40: HSE | F40: Alpha Abras | G40: Spot | H40: Material Normal | I40: =IFERROR(VLOOKUP(H40,SLA_Ref!$A$1:$B$8,2,FALSE),"") -> 8 | J40: =IF(A40="","",IF(B40="",IF(TODAY()-A40>I40,"ATRASADA","EM ANDAMENTO"),IF(B40-A40>I40,"ATRASADA","NO PRAZO"))) -> NO PRAZO | K40: =Tabela2[[#This Row],[SLA Padrão]]-Tabela2[[#This Row],[SLA Atendimento]] -> 5 | M40: 179 | N40: 161 | O40: BRL | P40: =Tabela2[[#This Row],[Proposta Inicial]]-Tabela2[[#This Row],[Proposta Negociada]] -> 18 | Q40: =Tabela2[[#This Row],[Proposta Negociada]]/Tabela2[[#This Row],[Proposta Inicial]]-1 -> -0.10055866 | R40: Cost Avoidance | S40: RC 10001729 - EPI - Kit Eco Florestal Genesis Capacete L340c Malha Plástica Adaptador Libus | T40: 450000265 | W40: 214583 | X40: Sim | Y40: Sim
A41: 46216 | B41: 46216 | C41: =IF(OR(A41="",B41=""),"",B41-A41) -> 0 | D41: Amanda Salvi | E41: CAPEX | F41: Dionezio Teixeira Bastos EPP | G41: Spot | H41: Regularização | I41: =IFERROR(VLOOKUP(H41,SLA_Ref!$A$1:$B$8,2,FALSE),"") -> 30 | J41: NO PRAZO | K41: 0 | M41: 275.69 | N41: 275.69 | O41: BRL | P41: =Tabela2[[#This Row],[Proposta Inicial]]-Tabela2[[#This Row],[Proposta Negociada]] -> 0 | Q41: =Tabela2[[#This Row],[Proposta Negociada]]/Tabela2[[#This Row],[Proposta Inicial]]-1 -> 0 | S41: Aquisição de cantoneiras para suportes elétrica | T41: 450000266 | X41: Sim | Y41: Sim
A42: 46213 | B42: 46216 | C42: =IF(OR(A42="",B42=""),"",B42-A42) -> 3 | D42: Michel Bernardes | E42: MKT | F42: Mais Você | G42: Spot | H42: Material Urgente | I42: =IFERROR(VLOOKUP(H42,SLA_Ref!$A$1:$B$8,2,FALSE),"") -> 3 | J42: =IF(A42="","",IF(B42="",IF(TODAY()-A42>I42,"ATRASADA","EM ANDAMENTO"),IF(B42-A42>I42,"ATRASADA","NO PRAZO"))) -> NO PRAZO | K42: =Tabela2[[#This Row],[SLA Padrão]]-Tabela2[[#This Row],[SLA Atendimento]] -> 0 | M42: 4796.6 | N42: 4796.6 | O42: BRL | P42: =Tabela2[[#This Row],[Proposta Inicial]]-Tabela2[[#This Row],[Proposta Negociada]] -> 0 | Q42: =Tabela2[[#This Row],[Proposta Negociada]]/Tabela2[[#This Row],[Proposta Inicial]]-1 -> 0 | S42: RC 10001728 - Patrocínio - Blusas Festival de Inverno | Marketing | T42: 450000267 | W42: 3181 | X42: Sim | Y42: Sim
A43: 46215 | B43: 46215 | C43: =IF(OR(A43="",B43=""),"",B43-A43) -> 0 | D43: Michel Bernardes | E43: CPTR | F43: Boreal Embalagens | G43: Spot | H43: Material Urgente | I43: =IFERROR(VLOOKUP(H43,SLA_Ref!$A$1:$B$8,2,FALSE),"") -> 3 | J43: =IF(A43="","",IF(B43="",IF(TODAY()-A43>I43,"ATRASADA","EM ANDAMENTO"),IF(B43-A43>I43,"ATRASADA","NO PRAZO"))) -> NO PRAZO | K43: =Tabela2[[#This Row],[SLA Padrão]]-Tabela2[[#This Row],[SLA Atendimento]] -> 3 | M43: 141.8 | N43: 141.8 | O43: BRL | P43: =Tabela2[[#This Row],[Proposta Inicial]]-Tabela2[[#This Row],[Proposta Negociada]] -> 0 | Q43: =Tabela2[[#This Row],[Proposta Negociada]]/Tabela2[[#This Row],[Proposta Inicial]]-1 -> 0 | S43: RC 10001726 - Sacos plásticos para laboratório – CPTR | T43: 450000268 | W43: 51003 | X43: SIM | Y43: Não
A44: 46213 | B44: 46216 | C44: =IF(OR(A44="",B44=""),"",B44-A44) -> 3 | D44: Amanda Salvi | E44: ADMINISTRATIVE | F44: Magma Industria e Comercio de cafe Ltda | G44: Spot | H44: Material Normal | I44: =IFERROR(VLOOKUP(H44,SLA_Ref!$A$1:$B$8,2,FALSE),"") -> 8 | J44: =IF(A44="","",IF(B44="",IF(TODAY()-A44>I44,"ATRASADA","EM ANDAMENTO"),IF(B44-A44>I44,"ATRASADA","NO PRAZO"))) -> NO PRAZO | K44: =Tabela2[[#This Row],[SLA Padrão]]-Tabela2[[#This Row],[SLA Atendimento]] -> 5 | M44: 1344 | N44: 1344 | O44: BRL | P44: =Tabela2[[#This Row],[Proposta Inicial]]-Tabela2[[#This Row],[Proposta Negociada]] -> 0 | Q44: =Tabela2[[#This Row],[Proposta Negociada]]/Tabela2[[#This Row],[Proposta Inicial]]-1 -> 0 | S44: RC 10001730 - Café Grãos | T44: 450000269 | W44: 1904 | X44: Sim | Y44: Sim
A45: 46215 | B45: 46215 | C45: =IF(OR(A45="",B45=""),"",B45-A45) -> 0 | D45: Michel Bernardes | E45: CPTR | F45: BRUNEPACK COMERCIO DE EMBALAGENS | G45: Spot | H45: Material Urgente | I45: =IFERROR(VLOOKUP(H45,SLA_Ref!$A$1:$B$8,2,FALSE),"") -> 3 | J45: =IF(A45="","",IF(B45="",IF(TODAY()-A45>I45,"ATRASADA","EM ANDAMENTO"),IF(B45-A45>I45,"ATRASADA","NO PRAZO"))) -> NO PRAZO | K45: =Tabela2[[#This Row],[SLA Padrão]]-Tabela2[[#This Row],[SLA Atendimento]] -> 3 | M45: 1917.51 | N45: 1450.4 | O45: BRL | P45: =Tabela2[[#This Row],[Proposta Inicial]]-Tabela2[[#This Row],[Proposta Negociada]] -> 467.11 | Q45: =Tabela2[[#This Row],[Proposta Negociada]]/Tabela2[[#This Row],[Proposta Inicial]]-1 -> -0.24360238 | R45: Cost Avoidance | S45: RC 10001726 - Sacos plásticos para laboratório – CPTR | T45: 450000270 | W45: 2262 | X45: Sim | Y45: Não
A46: 46205 | B46: 46213 | C46: =IF(OR(A46="",B46=""),"",B46-A46) -> 8 | D46: Amanda Salvi | E46: CPTR | F46: Agrosul Ltda | G46: Spot | H46: Material Normal | I46: =IFERROR(VLOOKUP(H46,SLA_Ref!$A$1:$B$8,2,FALSE),"") -> 8 | J46: =IF(A46="","",IF(B46="",IF(TODAY()-A46>I46,"ATRASADA","EM ANDAMENTO"),IF(B46-A46>I46,"ATRASADA","NO PRAZO"))) -> NO PRAZO | K46: =Tabela2[[#This Row],[SLA Padrão]]-Tabela2[[#This Row],[SLA Atendimento]] -> 0 | M46: 360 | N46: 360 | O46: BRL | P46: =Tabela2[[#This Row],[Proposta Inicial]]-Tabela2[[#This Row],[Proposta Negociada]] -> 0 | Q46: =Tabela2[[#This Row],[Proposta Negociada]]/Tabela2[[#This Row],[Proposta Inicial]]-1 -> 0 | S46: RC 10001684 - Sulfato de Amônio (AmSul) para operação – CPTR | T46: 450000271 | W46: 4070 | X46: Sim | Y46: Sim
A47: 46212 | B47: 46212 | C47: =IF(OR(A47="",B47=""),"",B47-A47) -> 0 | D47: Amanda Salvi | E47: ADMINISTRATIVE | F47: Sodre Miguel | G47: Spot | H47: Material Normal | I47: =IFERROR(VLOOKUP(H47,SLA_Ref!$A$1:$B$8,2,FALSE),"") -> 8 | J47: =IF(A47="","",IF(B47="",IF(TODAY()-A47>I47,"ATRASADA","EM ANDAMENTO"),IF(B47-A47>I47,"ATRASADA","NO PRAZO"))) -> NO PRAZO | K47: =Tabela2[[#This Row],[SLA Padrão]]-Tabela2[[#This Row],[SLA Atendimento]] -> 8 | M47: 508 | N47: 508 | O47: BRL | P47: =Tabela2[[#This Row],[Proposta Inicial]]-Tabela2[[#This Row],[Proposta Negociada]] -> 0 | Q47: =Tabela2[[#This Row],[Proposta Negociada]]/Tabela2[[#This Row],[Proposta Inicial]]-1 -> 0 | S47: RC 10001725 - Reposição Café Argentina Mall | T47: 450000272 | W47: 26362 | X47: Sim | Y47: Sim
A48: 46204 | B48: 46216 | C48: =IF(OR(A48="",B48=""),"",B48-A48) -> 12 | D48: Amanda Salvi | E48: GEOLOGICAL EXPLORATION | F48: Netlab Equipamentos para laboratorios Ltda | G48: Spot | H48: Material Urgente | I48: =IFERROR(VLOOKUP(H48,SLA_Ref!$A$1:$B$8,2,FALSE),"") -> 3 | J48: =IF(A48="","",IF(B48="",IF(TODAY()-A48>I48,"ATRASADA","EM ANDAMENTO"),IF(B48-A48>I48,"ATRASADA","NO PRAZO"))) -> ATRASADA | K48: =Tabela2[[#This Row],[SLA Padrão]]-Tabela2[[#This Row],[SLA Atendimento]] -> -9 | M48: 195.78 | N48: 195.78 | O48: BRL | P48: =Tabela2[[#This Row],[Proposta Inicial]]-Tabela2[[#This Row],[Proposta Negociada]] -> 0 | Q48: =Tabela2[[#This Row],[Proposta Negociada]]/Tabela2[[#This Row],[Proposta Inicial]]-1 -> 0 | S48: RC 10001674 - Compra de Silica Gel Azul | T48: 450000273 | W48: 129373 | X48: Sim | Y48: Não
A49: 46215 | B49: 46216 | C49: =IF(OR(A49="",B49=""),"",B49-A49) -> 1 | D49: Amanda Salvi | E49: CPTR | F49: Sodre Miguel | G49: Spot | H49: Material Normal | I49: =IFERROR(VLOOKUP(H49,SLA_Ref!$A$1:$B$8,2,FALSE),"") -> 8 | J49: =IF(A49="","",IF(B49="",IF(TODAY()-A49>I49,"ATRASADA","EM ANDAMENTO"),IF(B49-A49>I49,"ATRASADA","NO PRAZO"))) -> NO PRAZO | K49: =Tabela2[[#This Row],[SLA Padrão]]-Tabela2[[#This Row],[SLA Atendimento]] -> 7 | M49: 448.65 | N49: 448.65 | O49: BRL | P49: =Tabela2[[#This Row],[Proposta Inicial]]-Tabela2[[#This Row],[Proposta Negociada]] -> 0 | Q49: =Tabela2[[#This Row],[Proposta Negociada]]/Tabela2[[#This Row],[Proposta Inicial]]-1 -> 0 | S49: RC 10001715 - Reposição insumos para copa e limpeza – CPTR | T49: 450000274 | X49: Não | Y49: Sim
A50: 46215 | B50: 46216 | C50: =IF(OR(A50="",B50=""),"",B50-A50) -> 1 | D50: Amanda Salvi | E50: CPTR | F50: Disk Limpeza Total Ltda | G50: Spot | H50: Material Normal | I50: =IFERROR(VLOOKUP(H50,SLA_Ref!$A$1:$B$8,2,FALSE),"") -> 8 | J50: =IF(A50="","",IF(B50="",IF(TODAY()-A50>I50,"ATRASADA","EM ANDAMENTO"),IF(B50-A50>I50,"ATRASADA","NO PRAZO"))) -> NO PRAZO | K50: =Tabela2[[#This Row],[SLA Padrão]]-Tabela2[[#This Row],[SLA Atendimento]] -> 7 | M50: 224 | N50: 224 | O50: BRL | P50: =Tabela2[[#This Row],[Proposta Inicial]]-Tabela2[[#This Row],[Proposta Negociada]] -> 0 | Q50: =Tabela2[[#This Row],[Proposta Negociada]]/Tabela2[[#This Row],[Proposta Inicial]]-1 -> 0 | S50: RC 10001715 - Reposição insumos para copa e limpeza – CPTR | T50: 450000275 | W50: 25351 | X50: Sim | Y50: Sim
A51: 46217 | B51: 46213 | C51: =IF(OR(A51="",B51=""),"",B51-A51) -> -4 | D51: Amanda Salvi | E51: CPTR | F51: Caldasfer Ltda | G51: Spot | H51: Serviço Urgente | I51: =IFERROR(VLOOKUP(H51,SLA_Ref!$A$1:$B$8,2,FALSE),"") -> 5 | J51: =IF(A51="","",IF(B51="",IF(TODAY()-A51>I51,"ATRASADA","EM ANDAMENTO"),IF(B51-A51>I51,"ATRASADA","NO PRAZO"))) -> NO PRAZO | K51: =Tabela2[[#This Row],[SLA Padrão]]-Tabela2[[#This Row],[SLA Atendimento]] -> 9 | M51: 3000 | N51: 3000 | O51: BRL | P51: =Tabela2[[#This Row],[Proposta Inicial]]-Tabela2[[#This Row],[Proposta Negociada]] -> 0 | Q51: =Tabela2[[#This Row],[Proposta Negociada]]/Tabela2[[#This Row],[Proposta Inicial]]-1 -> 0 | S51: RC 10001733 - Tambores para transporte de minério – CPTR | T51: 450000277 | W51: 3595 | X51: Sim | Y51: Sim
A52: 46204 | B52: 46206 | C52: =IF(OR(A52="",B52=""),"",B52-A52) -> 2 | D52: Amanda Salvi | E52: ADMINISTRATIVE | F52: Tumei E-commerce Ltda | G52: Spot | H52: Material Normal | I52: =IFERROR(VLOOKUP(H52,SLA_Ref!$A$1:$B$8,2,FALSE),"") -> 8 | J52: =IF(A52="","",IF(B52="",IF(TODAY()-A52>I52,"ATRASADA","EM ANDAMENTO"),IF(B52-A52>I52,"ATRASADA","NO PRAZO"))) -> NO PRAZO | K52: =Tabela2[[#This Row],[SLA Padrão]]-Tabela2[[#This Row],[SLA Atendimento]] -> 6 | M52: 55 | N52: 55 | O52: BRL | P52: =Tabela2[[#This Row],[Proposta Inicial]]-Tabela2[[#This Row],[Proposta Negociada]] -> 0 | Q52: =Tabela2[[#This Row],[Proposta Negociada]]/Tabela2[[#This Row],[Proposta Inicial]]-1 -> 0 | S52: RC 10001691 - Reposição Estoque Papelaria | T52: 450000278 | W52: 7525 | X52: Sim | Y52: Não
A53: 46215 | B53: 46218 | C53: =IF(OR(A53="",B53=""),"",B53-A53) -> 3 | D53: Amanda Salvi | E53: CPTR | F53: Papelaria Bompapel Ltda | G53: Spot | H53: Material Normal | I53: =IFERROR(VLOOKUP(H53,SLA_Ref!$A$1:$B$8,2,FALSE),"") -> 8 | J53: =IF(A53="","",IF(B53="",IF(TODAY()-A53>I53,"ATRASADA","EM ANDAMENTO"),IF(B53-A53>I53,"ATRASADA","NO PRAZO"))) -> NO PRAZO | K53: =Tabela2[[#This Row],[SLA Padrão]]-Tabela2[[#This Row],[SLA Atendimento]] -> 5 | M53: 332.4 | N53: 332.4 | O53: BRL | P53: =Tabela2[[#This Row],[Proposta Inicial]]-Tabela2[[#This Row],[Proposta Negociada]] -> 0 | Q53: =Tabela2[[#This Row],[Proposta Negociada]]/Tabela2[[#This Row],[Proposta Inicial]]-1 -> 0 | S53: RC 10001724 - Materiais de Escritório – CPTR | T53: 450000279 | X53: Não | Y53: Sim
A54: 46215 | B54: 46218 | C54: =IF(OR(A54="",B54=""),"",B54-A54) -> 3 | D54: Amanda Salvi | E54: CPTR | F54: Papelaria Bompapel Ltda | G54: Spot | H54: Material Normal | I54: =IFERROR(VLOOKUP(H54,SLA_Ref!$A$1:$B$8,2,FALSE),"") -> 8 | J54: =IF(A54="","",IF(B54="",IF(TODAY()-A54>I54,"ATRASADA","EM ANDAMENTO"),IF(B54-A54>I54,"ATRASADA","NO PRAZO"))) -> NO PRAZO | K54: =Tabela2[[#This Row],[SLA Padrão]]-Tabela2[[#This Row],[SLA Atendimento]] -> 5 | M54: 269 | N54: 269 | O54: BRL | P54: =Tabela2[[#This Row],[Proposta Inicial]]-Tabela2[[#This Row],[Proposta Negociada]] -> 0 | Q54: =Tabela2[[#This Row],[Proposta Negociada]]/Tabela2[[#This Row],[Proposta Inicial]]-1 -> 0 | S54: RC 10001717 - Reposição folha sulfite A4 – CPTR | T54: 450000280 | X54: Não | Y54: Sim
A55: 46218 | B55: 46218 | C55: =IF(OR(A55="",B55=""),"",B55-A55) -> 0 | D55: Júlia Guidorizzi | E55: FINANCE | F55: ENGEP Engenharia e Perícia Ltda | G55: Spot | H55: Serviço Urgente | I55: =IFERROR(VLOOKUP(H55,SLA_Ref!$A$1:$B$8,2,FALSE),"") -> 5 | J55: =IF(A55="","",IF(B55="",IF(TODAY()-A55>I55,"ATRASADA","EM ANDAMENTO"),IF(B55-A55>I55,"ATRASADA","NO PRAZO"))) -> NO PRAZO | K55: =Tabela2[[#This Row],[SLA Padrão]]-Tabela2[[#This Row],[SLA Atendimento]] -> 5 | M55: 55000 | N55: 55000 | O55: BRL | P55: =Tabela2[[#This Row],[Proposta Inicial]]-Tabela2[[#This Row],[Proposta Negociada]] -> 0 | Q55: =Tabela2[[#This Row],[Proposta Negociada]]/Tabela2[[#This Row],[Proposta Inicial]]-1 -> 0 | S55: RC 10001748 - Laudo Técnico de Classificação Fiscal (NCM) | T55: 450000281 | X55: Não | Y55: Não
A56: 46218 | B56: 46218 | C56: =IF(OR(A56="",B56=""),"",B56-A56) -> 0 | D56: Júlia Guidorizzi | E56: CPTR | F56: BIG BAG LESTE PAULISTA LTDA | G56: Spot | H56: Material Urgente | I56: =IFERROR(VLOOKUP(H56,SLA_Ref!$A$1:$B$8,2,FALSE),"") -> 3 | J56: =IF(A56="","",IF(B56="",IF(TODAY()-A56>I56,"ATRASADA","EM ANDAMENTO"),IF(B56-A56>I56,"ATRASADA","NO PRAZO"))) -> NO PRAZO | K56: =Tabela2[[#This Row],[SLA Padrão]]-Tabela2[[#This Row],[SLA Atendimento]] -> 3 | L56: 3091.2 | M56: 3091.2 | N56: 2616 | O56: BRL | P56: =Tabela2[[#This Row],[Proposta Inicial]]-Tabela2[[#This Row],[Proposta Negociada]] -> 475.2 | Q56: =Tabela2[[#This Row],[Proposta Negociada]]/Tabela2[[#This Row],[Proposta Inicial]]-1 -> -0.15372671 | R56: Saving | S56: RC 10001747 - Reposição Big Bags 1T - CPTR | T56: 450000282 | W56: 1849 | X56: Sim | Y56: Não
A57: 46219 | B57: 46220 | C57: =IF(OR(A57="",B57=""),"",B57-A57) -> 1 | D57: Michel Bernardes | E57: CPTR | F57: Netlab Equipamentos para laboratorios Ltda | G57: Spot | H57: Material Normal | I57: =IFERROR(VLOOKUP(H57,SLA_Ref!$A$1:$B$8,2,FALSE),"") -> 8 | J57: =IF(A57="","",IF(B57="",IF(TODAY()-A57>I57,"ATRASADA","EM ANDAMENTO"),IF(B57-A57>I57,"ATRASADA","NO PRAZO"))) -> NO PRAZO | K57: =Tabela2[[#This Row],[SLA Padrão]]-Tabela2[[#This Row],[SLA Atendimento]] -> 7 | M57: 280.23 | N57: 280.23 | O57: BRL | P57: =Tabela2[[#This Row],[Proposta Inicial]]-Tabela2[[#This Row],[Proposta Negociada]] -> 0 | Q57: =Tabela2[[#This Row],[Proposta Negociada]]/Tabela2[[#This Row],[Proposta Inicial]]-1 -> 0 | S57: RC 10001742 - Cronômetros digitais para atividades laboratoriais e operacionais - CPTR | T57: 450000288 | X57: Não | Y57: Não
A58: 46219 | B58: 46220 | C58: =IF(OR(A58="",B58=""),"",B58-A58) -> 1 | D58: Michel Bernardes | E58: CPTR | F58: Print Green | G58: Spot | H58: Material Normal | I58: =IFERROR(VLOOKUP(H58,SLA_Ref!$A$1:$B$8,2,FALSE),"") -> 8 | J58: =IF(A58="","",IF(B58="",IF(TODAY()-A58>I58,"ATRASADA","EM ANDAMENTO"),IF(B58-A58>I58,"ATRASADA","NO PRAZO"))) -> NO PRAZO | K58: =Tabela2[[#This Row],[SLA Padrão]]-Tabela2[[#This Row],[SLA Atendimento]] -> 7 | M58: 79.16 | N58: 58.6 | O58: BRL | P58: =Tabela2[[#This Row],[Proposta Inicial]]-Tabela2[[#This Row],[Proposta Negociada]] -> 20.56 | Q58: =Tabela2[[#This Row],[Proposta Negociada]]/Tabela2[[#This Row],[Proposta Inicial]]-1 -> -0.25972713 | R58: Cost Avoidance | S58: RC 10001744 - Refil etiquetadora eletrônica - CPTR | T58: 450000289 | W58: 48694 | X58: SIM | Y58: Não
A59: 46219 | B59: 46220 | C59: =IF(OR(A59="",B59=""),"",B59-A59) -> 1 | D59: Michel Bernardes | E59: CPTR | F59: NELSON BEZERRA BASTOS | G59: Spot | H59: Material Normal | I59: =IFERROR(VLOOKUP(H59,SLA_Ref!$A$1:$B$8,2,FALSE),"") -> 8 | J59: =IF(A59="","",IF(B59="",IF(TODAY()-A59>I59,"ATRASADA","EM ANDAMENTO"),IF(B59-A59>I59,"ATRASADA","NO PRAZO"))) -> NO PRAZO | K59: =Tabela2[[#This Row],[SLA Padrão]]-Tabela2[[#This Row],[SLA Atendimento]] -> 7 | M59: 95 | N59: 95 | O59: BRL | P59: =Tabela2[[#This Row],[Proposta Inicial]]-Tabela2[[#This Row],[Proposta Negociada]] -> 0 | Q59: =Tabela2[[#This Row],[Proposta Negociada]]/Tabela2[[#This Row],[Proposta Inicial]]-1 -> 0 | S59: RC 10001752 - Abraçadeiras de nylon | T59: 450000290 | W59: 1486 | X59: Não | Y59: Não
A60: 46217 | B60: 46220 | C60: =IF(OR(A60="",B60=""),"",B60-A60) -> 3 | D60: Michel Bernardes | E60: HSE | F60: Copiativa | G60: Spot | H60: Material Normal | I60: =IFERROR(VLOOKUP(H60,SLA_Ref!$A$1:$B$8,2,FALSE),"") -> 8 | J60: =IF(A60="","",IF(B60="",IF(TODAY()-A60>I60,"ATRASADA","EM ANDAMENTO"),IF(B60-A60>I60,"ATRASADA","NO PRAZO"))) -> NO PRAZO | K60: =Tabela2[[#This Row],[SLA Padrão]]-Tabela2[[#This Row],[SLA Atendimento]] -> 5 | M60: 7426 | N60: 6000 | O60: BRL | P60: =Tabela2[[#This Row],[Proposta Inicial]]-Tabela2[[#This Row],[Proposta Negociada]] -> 1426 | Q60: =Tabela2[[#This Row],[Proposta Negociada]]/Tabela2[[#This Row],[Proposta Inicial]]-1 -> -0.19202801 | R60: Cost Avoidance | S60: RC 10001701 - Sinalização de segurança do CPTR | T60: 450000291 | X60: Não | Y60: Sim
A61: 46195 | B61: 46220 | C61: =IF(OR(A61="",B61=""),"",B61-A61) -> 25 | D61: Michel Bernardes | E61: ENVIRONMENT | F61: Als Brasil ltda | G61: Spot | H61: Contrato Contínuo Simples | I61: =IFERROR(VLOOKUP(H61,SLA_Ref!$A$1:$B$8,2,FALSE),"") -> 30 | J61: =IF(A61="","",IF(B61="",IF(TODAY()-A61>I61,"ATRASADA","EM ANDAMENTO"),IF(B61-A61>I61,"ATRASADA","NO PRAZO"))) -> NO PRAZO | K61: =Tabela2[[#This Row],[SLA Padrão]]-Tabela2[[#This Row],[SLA Atendimento]] -> 5 | M61: 3916.76 | N61: 1479.76 | O61: BRL | P61: =Tabela2[[#This Row],[Proposta Inicial]]-Tabela2[[#This Row],[Proposta Negociada]] -> 2437 | Q61: =Tabela2[[#This Row],[Proposta Negociada]]/Tabela2[[#This Row],[Proposta Inicial]]-1 -> -0.62219794 | R61: Cost Avoidance | S61: RC 10001608 - Coleta de Efluente - CPTR | T61: 450000292 | X61: Não | Y61: Não
A62: 46219 | B62: 46220 | C62: =IF(OR(A62="",B62=""),"",B62-A62) -> 1 | D62: Michel Bernardes | E62: GEOLOGICAL EXPLORATION | F62: R.R. DE MORAES ART | G62: Spot | H62: Material Normal | I62: =IFERROR(VLOOKUP(H62,SLA_Ref!$A$1:$B$8,2,FALSE),"") -> 8 | J62: =IF(A62="","",IF(B62="",IF(TODAY()-A62>I62,"ATRASADA","EM ANDAMENTO"),IF(B62-A62>I62,"ATRASADA","NO PRAZO"))) -> NO PRAZO | K62: =Tabela2[[#This Row],[SLA Padrão]]-Tabela2[[#This Row],[SLA Atendimento]] -> 7 | M62: =227.98+31.99 -> 259.97 | N62: 227.98 | O62: BRL | P62: =Tabela2[[#This Row],[Proposta Inicial]]-Tabela2[[#This Row],[Proposta Negociada]] -> 31.99 | Q62: =Tabela2[[#This Row],[Proposta Negociada]]/Tabela2[[#This Row],[Proposta Inicial]]-1 -> -0.12305266 | R62: Cost Avoidance | S62: RC 10001754 - Armário de chaves | T62: 450000293 | W62: 220584 | X62: Sim | Y62: Não
A63: 46220 | B63: 46220 | C63: =IF(OR(A63="",B63=""),"",B63-A63) -> 0 | D63: Michel Bernardes | E63: COMMUNITY RELATIONS | F63: Mais Você | G63: Spot | H63: Material Urgente | I63: =IFERROR(VLOOKUP(H63,SLA_Ref!$A$1:$B$8,2,FALSE),"") -> 3 | J63: =IF(A63="","",IF(B63="",IF(TODAY()-A63>I63,"ATRASADA","EM ANDAMENTO"),IF(B63-A63>I63,"ATRASADA","NO PRAZO"))) -> NO PRAZO | K63: =Tabela2[[#This Row],[SLA Padrão]]-Tabela2[[#This Row],[SLA Atendimento]] -> 3 | M63: =54.9*16 -> 878.4 | N63: 718.4 | O63: BRL | P63: =Tabela2[[#This Row],[Proposta Inicial]]-Tabela2[[#This Row],[Proposta Negociada]] -> 160 | Q63: =Tabela2[[#This Row],[Proposta Negociada]]/Tabela2[[#This Row],[Proposta Inicial]]-1 -> -0.18214936 | R63: Cost Avoidance | S63: RC 10001772 - Camisetas para o Edital Viridis + Comunidades | T63: 450000294 | W63: 3186 | X63: Não | Y63: Sim
A64: 46220 | B64: 46220 | C64: =IF(OR(A64="",B64=""),"",B64-A64) -> 0 | D64: Michel Bernardes | E64: COMMUNITY RELATIONS | F64: Nogueira | G64: Spot | H64: Material Urgente | I64: =IFERROR(VLOOKUP(H64,SLA_Ref!$A$1:$B$8,2,FALSE),"") -> 3 | J64: =IF(A64="","",IF(B64="",IF(TODAY()-A64>I64,"ATRASADA","EM ANDAMENTO"),IF(B64-A64>I64,"ATRASADA","NO PRAZO"))) -> NO PRAZO | K64: =Tabela2[[#This Row],[SLA Padrão]]-Tabela2[[#This Row],[SLA Atendimento]] -> 3 | M64: =936.18*2+214 -> 2086.36 | N64: =936.18*2 -> 1872.36 | O64: BRL | P64: =Tabela2[[#This Row],[Proposta Inicial]]-Tabela2[[#This Row],[Proposta Negociada]] -> 214 | Q64: =Tabela2[[#This Row],[Proposta Negociada]]/Tabela2[[#This Row],[Proposta Inicial]]-1 -> -0.10257098 | R64: Cost Avoidance | S64: RC 10001774 - Porta Banner | T64: 450000295 | W64: 19798 | X64: Sim | Y64: Não
A65: 46219 | B65: 46223 | C65: =IF(OR(A65="",B65=""),"",B65-A65) -> 4 | D65: Michel Bernardes | E65: GEOLOGICAL EXPLORATION | F65: arajocelene | G65: spot | H65: Material Normal | I65: =IFERROR(VLOOKUP(H65,SLA_Ref!$A$1:$B$8,2,FALSE),"") -> 8 | J65: =IF(A65="","",IF(B65="",IF(TODAY()-A65>I65,"ATRASADA","EM ANDAMENTO"),IF(B65-A65>I65,"ATRASADA","NO PRAZO"))) -> NO PRAZO | K65: =Tabela2[[#This Row],[SLA Padrão]]-Tabela2[[#This Row],[SLA Atendimento]] -> 4 | M65: 1601.5 | N65: 1558.8 | O65: BRL | P65: =Tabela2[[#This Row],[Proposta Inicial]]-Tabela2[[#This Row],[Proposta Negociada]] -> 42.7 | Q65: =Tabela2[[#This Row],[Proposta Negociada]]/Tabela2[[#This Row],[Proposta Inicial]]-1 -> -0.026662504 | R65: Cost Avoidance | S65: RC 10001752 - Abraçadeiras de nylon | T65: 450000296 | X65: Não | Y65: Não
A66: 46219 | B66: 46223 | C66: =IF(OR(A66="",B66=""),"",B66-A66) -> 4 | D66: Michel Bernardes | E66: HSE | F66: Alpha Abras | G66: Spot | H66: Material Normal | I66: =IFERROR(VLOOKUP(H66,SLA_Ref!$A$1:$B$8,2,FALSE),"") -> 8 | J66: =IF(A66="","",IF(B66="",IF(TODAY()-A66>I66,"ATRASADA","EM ANDAMENTO"),IF(B66-A66>I66,"ATRASADA","NO PRAZO"))) -> NO PRAZO | K66: =Tabela2[[#This Row],[SLA Padrão]]-Tabela2[[#This Row],[SLA Atendimento]] -> 4 | M66: 693.35 | N66: 673.8 | O66: BRL | P66: =Tabela2[[#This Row],[Proposta Inicial]]-Tabela2[[#This Row],[Proposta Negociada]] -> 19.55 | Q66: =Tabela2[[#This Row],[Proposta Negociada]]/Tabela2[[#This Row],[Proposta Inicial]]-1 -> -0.028196438 | R66: Cost Avoidance | S66: RC 10001751 - Reposição de Estoque de EPIs - CPTR | T66: 450000298 | W66: 215073 | X66: Sim | Y66: Sim
A67: 46219 | B67: 46223 | C67: =IF(OR(A67="",B67=""),"",B67-A67) -> 4 | D67: Michel Bernardes | E67: HSE | F67: Prot Cap | G67: Spot | H67: Material Normal | I67: =IFERROR(VLOOKUP(H67,SLA_Ref!$A$1:$B$8,2,FALSE),"") -> 8 | J67: =IF(A67="","",IF(B67="",IF(TODAY()-A67>I67,"ATRASADA","EM ANDAMENTO"),IF(B67-A67>I67,"ATRASADA","NO PRAZO"))) -> NO PRAZO | K67: =Tabela2[[#This Row],[SLA Padrão]]-Tabela2[[#This Row],[SLA Atendimento]] -> 4 | M67: 916.6 | N67: 916.6 | O67: BRL | P67: =Tabela2[[#This Row],[Proposta Inicial]]-Tabela2[[#This Row],[Proposta Negociada]] -> 0 | Q67: =Tabela2[[#This Row],[Proposta Negociada]]/Tabela2[[#This Row],[Proposta Inicial]]-1 -> 0 | S67: RC 10001751 - Reposição de Estoque de EPIs - CPTR | T67: 450000299 | X67: Não | Y67: Não
A68: 46220 | B68: 46223 | C68: =IF(OR(A68="",B68=""),"",B68-A68) -> 3 | D68: Michel Bernardes | E68: HSE | F68: DV Óculos de Segurança | G68: Spot | H68: Material Normal | I68: =IFERROR(VLOOKUP(H68,SLA_Ref!$A$1:$B$8,2,FALSE),"") -> 8 | J68: =IF(A68="","",IF(B68="",IF(TODAY()-A68>I68,"ATRASADA","EM ANDAMENTO"),IF(B68-A68>I68,"ATRASADA","NO PRAZO"))) -> NO PRAZO | K68: =Tabela2[[#This Row],[SLA Padrão]]-Tabela2[[#This Row],[SLA Atendimento]] -> 5 | M68: 2173.37 | N68: 2173.37 | O68: BRL | P68: =Tabela2[[#This Row],[Proposta Inicial]]-Tabela2[[#This Row],[Proposta Negociada]] -> 0 | Q68: =Tabela2[[#This Row],[Proposta Negociada]]/Tabela2[[#This Row],[Proposta Inicial]]-1 -> 0 | S68: RC 10001771 - Aquisição de óculos de segurança de grau para os colaboradores do CPTR | T68: 450000300 | X68: Não | Y68: Sim
A69: 46210 | B69: 46223 | C69: =IF(OR(A69="",B69=""),"",B69-A69) -> 13 | D69: Júlia Guidorizzi | E69: CPTR | F69: Dinâmica Assessoria em Documentos | G69: Spot | H69: Serviço Normal | I69: =IFERROR(VLOOKUP(H69,SLA_Ref!$A$1:$B$8,2,FALSE),"") -> 15 | J69: =IF(A69="","",IF(B69="",IF(TODAY()-A69>I69,"ATRASADA","EM ANDAMENTO"),IF(B69-A69>I69,"ATRASADA","NO PRAZO"))) -> NO PRAZO | K69: =Tabela2[[#This Row],[SLA Padrão]]-Tabela2[[#This Row],[SLA Atendimento]] -> 2 | M69: 7190 | N69: 7050 | O69: BRL | P69: =Tabela2[[#This Row],[Proposta Inicial]]-Tabela2[[#This Row],[Proposta Negociada]] -> 140 | Q69: =Tabela2[[#This Row],[Proposta Negociada]]/Tabela2[[#This Row],[Proposta Inicial]]-1 -> -0.019471488 | R69: Cost Avoidance | S69: RC 10001646 - Documentação p/ compra Ácido Clorídrico e Nítrico (PF, PC e Exército) | T69: 450000301 | X69: Não | Y69: Não
A70: 46223 | B70: 46223 | C70: =IF(OR(A70="",B70=""),"",B70-A70) -> 0 | D70: Michel Bernardes | E70: COMMUNITY RELATIONS | F70: Carolini Araujo | G70: Spot | H70: Material Urgente | I70: =IFERROR(VLOOKUP(H70,SLA_Ref!$A$1:$B$8,2,FALSE),"") -> 3 | J70: =IF(A70="","",IF(B70="",IF(TODAY()-A70>I70,"ATRASADA","EM ANDAMENTO"),IF(B70-A70>I70,"ATRASADA","NO PRAZO"))) -> NO PRAZO | K70: =Tabela2[[#This Row],[SLA Padrão]]-Tabela2[[#This Row],[SLA Atendimento]] -> 3 | M70: =225*12 -> 2700 | N70: =200*12 -> 2400 | O70: BRL | P70: =Tabela2[[#This Row],[Proposta Inicial]]-Tabela2[[#This Row],[Proposta Negociada]] -> 300 | Q70: =Tabela2[[#This Row],[Proposta Negociada]]/Tabela2[[#This Row],[Proposta Inicial]]-1 -> -0.11111111 | R70: Cost Avoidance | S70: RC 10001776 - Banner para Projetos Sociais apoiados pelo Edital Viridis + Comunidades | T70: 450000302 | W70: 237 | X70: Sim | Y70: Sim
A71: 46220 | B71: 46223 | C71: =IF(OR(A71="",B71=""),"",B71-A71) -> 3 | D71: Michel Bernardes | E71: IT | F71: BluePex | G71: Spot | H71: Serviço Urgente | I71: =IFERROR(VLOOKUP(H71,SLA_Ref!$A$1:$B$8,2,FALSE),"") -> 5 | J71: =IF(A71="","",IF(B71="",IF(TODAY()-A71>I71,"ATRASADA","EM ANDAMENTO"),IF(B71-A71>I71,"ATRASADA","NO PRAZO"))) -> NO PRAZO | K71: =Tabela2[[#This Row],[SLA Padrão]]-Tabela2[[#This Row],[SLA Atendimento]] -> 2 | M71: 159.5 | N71: 90 | O71: BRL | P71: =Tabela2[[#This Row],[Proposta Inicial]]-Tabela2[[#This Row],[Proposta Negociada]] -> 69.5 | Q71: =Tabela2[[#This Row],[Proposta Negociada]]/Tabela2[[#This Row],[Proposta Inicial]]-1 -> -0.43573668 | R71: Cost Avoidance | S71: RC 10001763 - 10 Licenças EndPoint BluePex | T71: 450000303 | X71: Não | Y71: Não
A72: 46223 | B72: 46223 | C72: =IF(OR(A72="",B72=""),"",B72-A72) -> 0 | D72: Michel Bernardes | E72: CPTR | F72: Emplasul | G72: Spot | H72: Material Urgente | I72: =IFERROR(VLOOKUP(H72,SLA_Ref!$A$1:$B$8,2,FALSE),"") -> 3 | J72: =IF(A72="","",IF(B72="",IF(TODAY()-A72>I72,"ATRASADA","EM ANDAMENTO"),IF(B72-A72>I72,"ATRASADA","NO PRAZO"))) -> NO PRAZO | K72: =Tabela2[[#This Row],[SLA Padrão]]-Tabela2[[#This Row],[SLA Atendimento]] -> 3 | M72: =850*6 -> 5100 | N72: =850*6 -> 5100 | O72: BRL | P72: =Tabela2[[#This Row],[Proposta Inicial]]-Tabela2[[#This Row],[Proposta Negociada]] -> 0 | Q72: =Tabela2[[#This Row],[Proposta Negociada]]/Tabela2[[#This Row],[Proposta Inicial]]-1 -> 0 | S72: RC 10001766 - Compra emergencial IBCs - CPTR | T72: 450000304 | W72: 50441 | X72: Sim | Y72: Não
A73: 46220 | B73: 46223 | C73: =IF(OR(A73="",B73=""),"",B73-A73) -> 3 | D73: Michel Bernardes | E73: HSE | F73: Alpha Abras | G73: Spot | H73: Material Normal | I73: =IFERROR(VLOOKUP(H73,SLA_Ref!$A$1:$B$8,2,FALSE),"") -> 8 | J73: =IF(A73="","",IF(B73="",IF(TODAY()-A73>I73,"ATRASADA","EM ANDAMENTO"),IF(B73-A73>I73,"ATRASADA","NO PRAZO"))) -> NO PRAZO | K73: =Tabela2[[#This Row],[SLA Padrão]]-Tabela2[[#This Row],[SLA Atendimento]] -> 5 | M73: 87 | N73: 80.9 | O73: BRL | P73: =Tabela2[[#This Row],[Proposta Inicial]]-Tabela2[[#This Row],[Proposta Negociada]] -> 6.1 | Q73: =Tabela2[[#This Row],[Proposta Negociada]]/Tabela2[[#This Row],[Proposta Inicial]]-1 -> -0.070114943 | R73: Cost Avoidance | S73: RC 10001755 - Corrente e cadeado para porteiras | T73: 450000306 | W73: 215164 | X73: Sim | Y73: Sim
A74: 46220 | B74: 46223 | C74: =IF(OR(A74="",B74=""),"",B74-A74) -> 3 | D74: Michel Bernardes | E74: HSE | F74: Alpha Abras | G74: Spot | H74: Material Normal | I74: =IFERROR(VLOOKUP(H74,SLA_Ref!$A$1:$B$8,2,FALSE),"") -> 8 | J74: =IF(A74="","",IF(B74="",IF(TODAY()-A74>I74,"ATRASADA","EM ANDAMENTO"),IF(B74-A74>I74,"ATRASADA","NO PRAZO"))) -> NO PRAZO | K74: =Tabela2[[#This Row],[SLA Padrão]]-Tabela2[[#This Row],[SLA Atendimento]] -> 5 | M74: =682.12+149.9 -> 832.02 | N74: 682.12 | O74: BRL | P74: =Tabela2[[#This Row],[Proposta Inicial]]-Tabela2[[#This Row],[Proposta Negociada]] -> 149.9 | Q74: =Tabela2[[#This Row],[Proposta Negociada]]/Tabela2[[#This Row],[Proposta Inicial]]-1 -> -0.18016394 | R74: Cost Avoidance | S74: RC 10001775 - Aquisição de EPIS para reposição no estoque atividades Exploração | T74: 450000307 | X74: Não | Y74: Sim
A75: 46223 | B75: 46224 | C75: =IF(OR(A75="",B75=""),"",B75-A75) -> 1 | D75: Michel Bernardes | E75: HSE | F75: Total Safety | G75: Spot | H75: Serviço Normal | I75: =IFERROR(VLOOKUP(H75,SLA_Ref!$A$1:$B$8,2,FALSE),"") -> 15 | J75: =IF(A75="","",IF(B75="",IF(TODAY()-A75>I75,"ATRASADA","EM ANDAMENTO"),IF(B75-A75>I75,"ATRASADA","NO PRAZO"))) -> NO PRAZO | K75: =Tabela2[[#This Row],[SLA Padrão]]-Tabela2[[#This Row],[SLA Atendimento]] -> 14 | M75: 3454.5 | N75: 3352.2 | O75: BRL | P75: =Tabela2[[#This Row],[Proposta Inicial]]-Tabela2[[#This Row],[Proposta Negociada]] -> 102.3 | Q75: =Tabela2[[#This Row],[Proposta Negociada]]/Tabela2[[#This Row],[Proposta Inicial]]-1 -> -0.029613548 | R75: Cost Avoidance | S75: RC 10001781 - Higienização dos Equipamentos de Proteção Individual (EPIs) destinados ao uso de visitantes. | T75: 450000309 | X75: Não | Y75: Sim
A76: 46224 | B76: 46225 | C76: =IF(OR(A76="",B76=""),"",B76-A76) -> 1 | D76: Michel Bernardes | E76: HSE | F76: Merli Lavanderia | G76: Spot | H76: Serviço Normal | I76: =IFERROR(VLOOKUP(H76,SLA_Ref!$A$1:$B$8,2,FALSE),"") -> 15 | J76: =IF(A76="","",IF(B76="",IF(TODAY()-A76>I76,"ATRASADA","EM ANDAMENTO"),IF(B76-A76>I76,"ATRASADA","NO PRAZO"))) -> NO PRAZO | K76: =Tabela2[[#This Row],[SLA Padrão]]-Tabela2[[#This Row],[SLA Atendimento]] -> 14 | M76: 224.75 | N76: 224.75 | O76: BRL | P76: =Tabela2[[#This Row],[Proposta Inicial]]-Tabela2[[#This Row],[Proposta Negociada]] -> 0 | Q76: =Tabela2[[#This Row],[Proposta Negociada]]/Tabela2[[#This Row],[Proposta Inicial]]-1 -> 0 | S76: RC 10001781 - Higienização dos Equipamentos de Proteção Individual (EPIs) destinados ao uso de visitantes. | T76: 450000315 | X76: Não | Y76: Sim
A77: 46206 | B77: 46226 | C77: =IF(OR(A77="",B77=""),"",B77-A77) -> 20 | D77: Júlia Guidorizzi | E77: CPTR | F77: Fluid Brasil Sistemas e Tecnologia Ltda | G77: Spot | H77: Material Normal | I77: =IFERROR(VLOOKUP(H77,SLA_Ref!$A$1:$B$8,2,FALSE),"") -> 8 | J77: =IF(A77="","",IF(B77="",IF(TODAY()-A77>I77,"ATRASADA","EM ANDAMENTO"),IF(B77-A77>I77,"ATRASADA","NO PRAZO"))) -> ATRASADA | K77: =Tabela2[[#This Row],[SLA Padrão]]-Tabela2[[#This Row],[SLA Atendimento]] -> -12 | M77: 2630 | N77: 2630 | O77: BRL | P77: =Tabela2[[#This Row],[Proposta Inicial]]-Tabela2[[#This Row],[Proposta Negociada]] -> 0 | Q77: =Tabela2[[#This Row],[Proposta Negociada]]/Tabela2[[#This Row],[Proposta Inicial]]-1 -> 0 | S77: Membrana reserva PROXA - segunda compra | T77: 450000317 | X77: Não | Y77: Não
A78: 46225 | B78: 46226 | C78: =IF(OR(A78="",B78=""),"",B78-A78) -> 1 | D78: Júlia Guidorizzi | E78: CPTR | F78: Fluid Brasil Sistemas e Tecnologia Ltda | G78: Spot | H78: Material Normal | I78: =IFERROR(VLOOKUP(H78,SLA_Ref!$A$1:$B$8,2,FALSE),"") -> 8 | J78: =IF(A78="","",IF(B78="",IF(TODAY()-A78>I78,"ATRASADA","EM ANDAMENTO"),IF(B78-A78>I78,"ATRASADA","NO PRAZO"))) -> NO PRAZO | K78: =Tabela2[[#This Row],[SLA Padrão]]-Tabela2[[#This Row],[SLA Atendimento]] -> 7 | M78: 8772.99 | N78: 8772.99 | O78: BRL | P78: =Tabela2[[#This Row],[Proposta Inicial]]-Tabela2[[#This Row],[Proposta Negociada]] -> 0 | Q78: =Tabela2[[#This Row],[Proposta Negociada]]/Tabela2[[#This Row],[Proposta Inicial]]-1 -> 0 | S78: Segregação de componentes químicos da PROXA - Segurança | T78: 450000317 | X78: Não | Y78: Não
A79: 46205 | B79: 46226 | C79: =IF(OR(A79="",B79=""),"",B79-A79) -> 21 | D79: Júlia Guidorizzi | E79: CPTR | F79: Fluid Brasil Sistemas e Tecnologia Ltda | G79: Spot | H79: Material Normal | I79: =IFERROR(VLOOKUP(H79,SLA_Ref!$A$1:$B$8,2,FALSE),"") -> 8 | J79: =IF(A79="","",IF(B79="",IF(TODAY()-A79>I79,"ATRASADA","EM ANDAMENTO"),IF(B79-A79>I79,"ATRASADA","NO PRAZO"))) -> ATRASADA | K79: =Tabela2[[#This Row],[SLA Padrão]]-Tabela2[[#This Row],[SLA Atendimento]] -> -13 | M79: 43517.04 | N79: 41335.38 | O79: BRL | P79: =Tabela2[[#This Row],[Proposta Inicial]]-Tabela2[[#This Row],[Proposta Negociada]] -> 2181.66 | Q79: =Tabela2[[#This Row],[Proposta Negociada]]/Tabela2[[#This Row],[Proposta Inicial]]-1 -> -0.050133465 | R79: Cost Avoidance | S79: Adequações segurança PROXA | T79: 450000317 | X79: Não | Y79: Não
A80: 46225 | B80: 46225 | C80: =IF(OR(A80="",B80=""),"",B80-A80) -> 0 | D80: Michel Bernardes | E80: ENVIRONMENT | F80: LOTUS CENTRAL DE DISTRIBUICAO DE HIGIENICOS LTDA | G80: Spot | H80: Material Normal | I80: =IFERROR(VLOOKUP(H80,SLA_Ref!$A$1:$B$8,2,FALSE),"") -> 8 | J80: =IF(A80="","",IF(B80="",IF(TODAY()-A80>I80,"ATRASADA","EM ANDAMENTO"),IF(B80-A80>I80,"ATRASADA","NO PRAZO"))) -> NO PRAZO | K80: =Tabela2[[#This Row],[SLA Padrão]]-Tabela2[[#This Row],[SLA Atendimento]] -> 8 | M80: 653.98 | N80: 653.98 | O80: BRL | P80: =Tabela2[[#This Row],[Proposta Inicial]]-Tabela2[[#This Row],[Proposta Negociada]] -> 0 | Q80: =Tabela2[[#This Row],[Proposta Negociada]]/Tabela2[[#This Row],[Proposta Inicial]]-1 -> 0 | S80: RC 10001757 - 02 Lixeiras 60L para o refeitório | T80: 450000318 | X80: Não | Y80: Não
A81: 46227 | B81: 46227 | C81: =IF(OR(A81="",B81=""),"",B81-A81) -> 0 | D81: Michel Bernardes | E81: CPTR | F81: Toque de Cor | G81: Spot | H81: Material Urgente | I81: =IFERROR(VLOOKUP(H81,SLA_Ref!$A$1:$B$8,2,FALSE),"") -> 3 | J81: =IF(A81="","",IF(B81="",IF(TODAY()-A81>I81,"ATRASADA","EM ANDAMENTO"),IF(B81-A81>I81,"ATRASADA","NO PRAZO"))) -> NO PRAZO | K81: =Tabela2[[#This Row],[SLA Padrão]]-Tabela2[[#This Row],[SLA Atendimento]] -> 3 | M81: 230 | N81: 184 | O81: BRL | P81: =Tabela2[[#This Row],[Proposta Inicial]]-Tabela2[[#This Row],[Proposta Negociada]] -> 46 | Q81: =Tabela2[[#This Row],[Proposta Negociada]]/Tabela2[[#This Row],[Proposta Inicial]]-1 -> -0.2 | S81: Tintas para pintura do caminho seguro do CPTR | T81: 450000325 | W81: 2018 | X81: Sim | Y81: Sim
A82: 46230 | B82: 46230 | C82: =IF(OR(A82="",B82=""),"",B82-A82) -> 0 | D82: Michel Bernardes | E82: HSE | F82: 1000 Marcas | G82: Spot | H82: Material Normal | I82: =IFERROR(VLOOKUP(H82,SLA_Ref!$A$1:$B$8,2,FALSE),"") -> 8 | J82: =IF(A82="","",IF(B82="",IF(TODAY()-A82>I82,"ATRASADA","EM ANDAMENTO"),IF(B82-A82>I82,"ATRASADA","NO PRAZO"))) -> NO PRAZO | K82: =Tabela2[[#This Row],[SLA Padrão]]-Tabela2[[#This Row],[SLA Atendimento]] -> 8 | M82: =266.9*7 -> 1868.3 | N82: 1793.61 | O82: BRL | P82: =Tabela2[[#This Row],[Proposta Inicial]]-Tabela2[[#This Row],[Proposta Negociada]] -> 74.69 | Q82: =Tabela2[[#This Row],[Proposta Negociada]]/Tabela2[[#This Row],[Proposta Inicial]]-1 -> -0.03997752 | R82: Cost Avoidance | S82: RC 10001812 - Botas de Segurança Anti Torção Marluvas CA 34.550 | T82: 450000333 | X82: Não | Y82: Não
A83: 46215 | B83: 46219 | C83: =IF(OR(A83="",B83=""),"",B83-A83) -> 4 | D83: Amanda Salvi | E83: CPTR | F83: Papelaria Bompapel Ltda | G83: Spot | H83: Material Normal | I83: =IFERROR(VLOOKUP(H83,SLA_Ref!$A$1:$B$8,2,FALSE),"") -> 8 | J83: =IF(A83="","",IF(B83="",IF(TODAY()-A83>I83,"ATRASADA","EM ANDAMENTO"),IF(B83-A83>I83,"ATRASADA","NO PRAZO"))) -> NO PRAZO | K83: =Tabela2[[#This Row],[SLA Padrão]]-Tabela2[[#This Row],[SLA Atendimento]] -> 4 | M83: 600 | N83: 580 | O83: BRL | P83: =Tabela2[[#This Row],[Proposta Inicial]]-Tabela2[[#This Row],[Proposta Negociada]] -> 20 | Q83: =Tabela2[[#This Row],[Proposta Negociada]]/Tabela2[[#This Row],[Proposta Inicial]]-1 -> -0.033333333 | S83: RC 10001716 - Reposição tinta para impressora HP Laser Color – CPTR | T83: 450000283 | W83: 1182 | X83: Sim | Y83: Sim
A84: 46220 | B84: 46219 | C84: =IF(OR(A84="",B84=""),"",B84-A84) -> -1 | D84: Amanda Salvi | E84: CAPEX | F84: Casa Dos Parafusos Industrial Ltda | G84: Spot | H84: Material Urgente | I84: =IFERROR(VLOOKUP(H84,SLA_Ref!$A$1:$B$8,2,FALSE),"") -> 3 | J84: =IF(A84="","",IF(B84="",IF(TODAY()-A84>I84,"ATRASADA","EM ANDAMENTO"),IF(B84-A84>I84,"ATRASADA","NO PRAZO"))) -> NO PRAZO | K84: =Tabela2[[#This Row],[SLA Padrão]]-Tabela2[[#This Row],[SLA Atendimento]] -> 4 | M84: 119.6 | N84: 119.6 | O84: BRL | P84: =Tabela2[[#This Row],[Proposta Inicial]]-Tabela2[[#This Row],[Proposta Negociada]] -> 0 | Q84: =Tabela2[[#This Row],[Proposta Negociada]]/Tabela2[[#This Row],[Proposta Inicial]]-1 -> 0 | S84: Parafusos para modificação Hopper CPTR | T84: 450000284 | W84: 1220 | X84: Sim | Y84: Sim
A85: 46219 | B85: 46219 | C85: =IF(OR(A85="",B85=""),"",B85-A85) -> 0 | D85: Amanda Salvi | E85: CPTR | F85: Anderson Aparecido Pinto | G85: Spot | H85: Material Urgente | I85: =IFERROR(VLOOKUP(H85,SLA_Ref!$A$1:$B$8,2,FALSE),"") -> 3 | J85: =IF(A85="","",IF(B85="",IF(TODAY()-A85>I85,"ATRASADA","EM ANDAMENTO"),IF(B85-A85>I85,"ATRASADA","NO PRAZO"))) -> NO PRAZO | K85: =Tabela2[[#This Row],[SLA Padrão]]-Tabela2[[#This Row],[SLA Atendimento]] -> 3 | M85: 149.8 | N85: 149.8 | O85: BRL | P85: =Tabela2[[#This Row],[Proposta Inicial]]-Tabela2[[#This Row],[Proposta Negociada]] -> 0 | Q85: =Tabela2[[#This Row],[Proposta Negociada]]/Tabela2[[#This Row],[Proposta Inicial]]-1 -> 0 | S85: RC 10001745 - Pilhas alcalinas AAA - CPTR | T85: 450000285 | W85: 1370 | X85: Sim | Y85: Não
A86: 46219 | B86: 46223 | C86: =IF(OR(A86="",B86=""),"",B86-A86) -> 4 | D86: Amanda Salvi | E86: CPTR | F86: Snf Brasil Comercial Quimica Ltda | G86: Spot | H86: Material Urgente | I86: =IFERROR(VLOOKUP(H86,SLA_Ref!$A$1:$B$8,2,FALSE),"") -> 3 | J86: =IF(A86="","",IF(B86="",IF(TODAY()-A86>I86,"ATRASADA","EM ANDAMENTO"),IF(B86-A86>I86,"ATRASADA","NO PRAZO"))) -> ATRASADA | K86: =Tabela2[[#This Row],[SLA Padrão]]-Tabela2[[#This Row],[SLA Atendimento]] -> -1 | M86: 535.77 | N86: 535.77 | O86: BRL | P86: =Tabela2[[#This Row],[Proposta Inicial]]-Tabela2[[#This Row],[Proposta Negociada]] -> 0 | Q86: =Tabela2[[#This Row],[Proposta Negociada]]/Tabela2[[#This Row],[Proposta Inicial]]-1 -> 0 | S86: RC 10001743 - Floculante 913 para o processo produtivo - CPTR | T86: 450000286 | W86: 137236 | X86: Sim | Y86: Não
A87: 46219 | B87: 46223 | C87: =IF(OR(A87="",B87=""),"",B87-A87) -> 4 | D87: Amanda Salvi | E87: GEOLOGICAL EXPLORATION | F87: Bentley Systems Brasil Ltda | G87: Spot | H87: Serviço Urgente | I87: =IFERROR(VLOOKUP(H87,SLA_Ref!$A$1:$B$8,2,FALSE),"") -> 5 | J87: =IF(A87="","",IF(B87="",IF(TODAY()-A87>I87,"ATRASADA","EM ANDAMENTO"),IF(B87-A87>I87,"ATRASADA","NO PRAZO"))) -> NO PRAZO | K87: =Tabela2[[#This Row],[SLA Padrão]]-Tabela2[[#This Row],[SLA Atendimento]] -> 1 | M87: 8098.33 | N87: 8098.33 | O87: BRL | P87: =Tabela2[[#This Row],[Proposta Inicial]]-Tabela2[[#This Row],[Proposta Negociada]] -> 0 | Q87: =Tabela2[[#This Row],[Proposta Negociada]]/Tabela2[[#This Row],[Proposta Inicial]]-1 -> 0 | S87: RC 10001687 - Licença do MX Deposit | T87: 450000287 | X87: Sim | Y87: Não
A88: 46219 | B88: 46230 | C88: =IF(OR(A88="",B88=""),"",B88-A88) -> 11 | D88: Amanda Salvi | E88: GEOLOGICAL EXPLORATION | F88: J Macedo | G88: Spot | H88: Material Normal | I88: =IFERROR(VLOOKUP(H88,SLA_Ref!$A$1:$B$8,2,FALSE),"") -> 8 | J88: =IF(A88="","",IF(B88="",IF(TODAY()-A88>I88,"ATRASADA","EM ANDAMENTO"),IF(B88-A88>I88,"ATRASADA","NO PRAZO"))) -> ATRASADA | K88: =Tabela2[[#This Row],[SLA Padrão]]-Tabela2[[#This Row],[SLA Atendimento]] -> -3 | M88: 10867.5 | N88: 10867.5 | O88: BRL | P88: =Tabela2[[#This Row],[Proposta Inicial]]-Tabela2[[#This Row],[Proposta Negociada]] -> 0 | Q88: =Tabela2[[#This Row],[Proposta Negociada]]/Tabela2[[#This Row],[Proposta Inicial]]-1 -> 0 | S88: RC 10001582 - Sacos plásticos 50 x 70 | T88: 450000296 | X88: Não | Y88: Não
A89: 46219 | B89: 46220 | C89: =Tabela2[[#This Row],[Data Pedido]]-Tabela2[[#This Row],[Data Última Aprovação RC]] -> 1 | D89: Michel Bernardes | E89: CPTR | F89: Nelson Bezerras Bastos | G89: Spot | H89: Material Normal | I89: =IFERROR(VLOOKUP(H89,SLA_Ref!$A$1:$B$8,2,FALSE),"") -> 8 | J89: =IF(A89="","",IF(B89="",IF(TODAY()-A89>I89,"ATRASADA","EM ANDAMENTO"),IF(B89-A89>I89,"ATRASADA","NO PRAZO"))) -> NO PRAZO | K89: =Tabela2[[#This Row],[SLA Padrão]]-Tabela2[[#This Row],[SLA Atendimento]] -> 7 | M89: 95 | N89: 95 | O89: BRL | P89: =Tabela2[[#This Row],[Proposta Inicial]]-Tabela2[[#This Row],[Proposta Negociada]] -> 0 | Q89: =Tabela2[[#This Row],[Proposta Negociada]]/Tabela2[[#This Row],[Proposta Inicial]]-1 -> 0 | S89: RC 10001741 - Papel filtro e abraçadeiras de nylon para uso laboratorial - CPTR | T89: 450000290 | W89: 1486 | X89: Sim | Y89: Não
A90: 46223 | B90: 46223 | C90: =IF(OR(A90="",B90=""),"",B90-A90) -> 0 | D90: Amanda Salvi | E90: CPTR | F90: Pergorari comercio de embalagens ltda | G90: Spot | H90: Material Urgente | I90: =IFERROR(VLOOKUP(H90,SLA_Ref!$A$1:$B$8,2,FALSE),"") -> 3 | J90: =IF(A90="","",IF(B90="",IF(TODAY()-A90>I90,"ATRASADA","EM ANDAMENTO"),IF(B90-A90>I90,"ATRASADA","NO PRAZO"))) -> NO PRAZO | K90: =Tabela2[[#This Row],[SLA Padrão]]-Tabela2[[#This Row],[SLA Atendimento]] -> 3 | M90: 318.8 | N90: 318.8 | O90: BRL | P90: =Tabela2[[#This Row],[Proposta Inicial]]-Tabela2[[#This Row],[Proposta Negociada]] -> 0 | Q90: =Tabela2[[#This Row],[Proposta Negociada]]/Tabela2[[#This Row],[Proposta Inicial]]-1 -> 0 | S90: RC 10001740 - Embalagens para envio de amostras de MRECs - CPTR | T90: 450000305 | W90: 7682 | X90: Sim | Y90: Não
A91: 46213 | B91: 46224 | C91: =IF(OR(A91="",B91=""),"",B91-A91) -> 11 | D91: Amanda Salvi | E91: CPTR | F91: Sherwin Williams do Brasil Industrial e Comercio Ltda | G91: Spot | H91: Material Normal | I91: =IFERROR(VLOOKUP(H91,SLA_Ref!$A$1:$B$8,2,FALSE),"") -> 8 | J91: =IF(A91="","",IF(B91="",IF(TODAY()-A91>I91,"ATRASADA","EM ANDAMENTO"),IF(B91-A91>I91,"ATRASADA","NO PRAZO"))) -> ATRASADA | K91: =Tabela2[[#This Row],[SLA Padrão]]-Tabela2[[#This Row],[SLA Atendimento]] -> -3 | M91: 1707.84 | N91: 1707.84 | O91: BRL | P91: =Tabela2[[#This Row],[Proposta Inicial]]-Tabela2[[#This Row],[Proposta Negociada]] -> 0 | Q91: =Tabela2[[#This Row],[Proposta Negociada]]/Tabela2[[#This Row],[Proposta Inicial]]-1 -> 0 | S91: Tintas para pintura do caminho seguro do CPTR | T91: 450000308 | X91: Sim | Y91: Sim
A92: 46224 | B92: 46225 | C92: =IF(OR(A92="",B92=""),"",B92-A92) -> 1 | D92: Amanda Salvi | E92: ADMINISTRATIVE | F92: Disk Limpeza Total Ltda | G92: Spot | H92: Material Normal | I92: =IFERROR(VLOOKUP(H92,SLA_Ref!$A$1:$B$8,2,FALSE),"") -> 8 | J92: =IF(A92="","",IF(B92="",IF(TODAY()-A92>I92,"ATRASADA","EM ANDAMENTO"),IF(B92-A92>I92,"ATRASADA","NO PRAZO"))) -> NO PRAZO | K92: =Tabela2[[#This Row],[SLA Padrão]]-Tabela2[[#This Row],[SLA Atendimento]] -> 7 | M92: 1045.71 | N92: 1045.71 | O92: BRL | P92: =Tabela2[[#This Row],[Proposta Inicial]]-Tabela2[[#This Row],[Proposta Negociada]] -> 0 | Q92: =Tabela2[[#This Row],[Proposta Negociada]]/Tabela2[[#This Row],[Proposta Inicial]]-1 -> 0 | S92: RC 10001789 - Itens de Limpeza - Argentina Mall | T92: 450000310 | W92: 25414 | X92: Sim | Y92: Sim
A93: 46217 | B93: 46223 | C93: =IF(OR(A93="",B93=""),"",B93-A93) -> 6 | D93: Amanda Salvi | E93: ADMINISTRATIVE | F93: Veronesi & Filhos Ltda | G93: Spot | H93: Material Normal | I93: =IFERROR(VLOOKUP(H93,SLA_Ref!$A$1:$B$8,2,FALSE),"") -> 8 | J93: =IF(A93="","",IF(B93="",IF(TODAY()-A93>I93,"ATRASADA","EM ANDAMENTO"),IF(B93-A93>I93,"ATRASADA","NO PRAZO"))) -> NO PRAZO | K93: =Tabela2[[#This Row],[SLA Padrão]]-Tabela2[[#This Row],[SLA Atendimento]] -> 2 | M93: 460 | N93: 460 | O93: BRL | P93: =Tabela2[[#This Row],[Proposta Inicial]]-Tabela2[[#This Row],[Proposta Negociada]] -> 0 | Q93: =Tabela2[[#This Row],[Proposta Negociada]]/Tabela2[[#This Row],[Proposta Inicial]]-1 -> 0 | S93: RC 10001735 - Blocos de requisição de combustível | T93: 450000311 | X93: Sim | Y93: Sim
A94: 46215 | B94: 46225 | C94: =IF(OR(A94="",B94=""),"",B94-A94) -> 10 | D94: Amanda Salvi | E94: CPTR | F94: Disk Limpeza Total Ltda | G94: Spot | H94: Material Normal | I94: =IFERROR(VLOOKUP(H94,SLA_Ref!$A$1:$B$8,2,FALSE),"") -> 8 | J94: =IF(A94="","",IF(B94="",IF(TODAY()-A94>I94,"ATRASADA","EM ANDAMENTO"),IF(B94-A94>I94,"ATRASADA","NO PRAZO"))) -> ATRASADA | K94: =Tabela2[[#This Row],[SLA Padrão]]-Tabela2[[#This Row],[SLA Atendimento]] -> -2 | M94: 95 | N94: 95 | O94: BRL | P94: =Tabela2[[#This Row],[Proposta Inicial]]-Tabela2[[#This Row],[Proposta Negociada]] -> 0 | Q94: =Tabela2[[#This Row],[Proposta Negociada]]/Tabela2[[#This Row],[Proposta Inicial]]-1 -> 0 | S94: RC 10001715 - Reposição insumos para copa e limpeza – CPTR | T94: 450000312 | X94: Sim | Y94: Sim
A95: 46224 | B95: 46230 | C95: =IF(OR(A95="",B95=""),"",B95-A95) -> 6 | D95: Amanda Salvi | E95: MINE PLANNING | F95: Sodre Miguel Ltda | G95: Spot | H95: Material Normal | I95: =IFERROR(VLOOKUP(H95,SLA_Ref!$A$1:$B$8,2,FALSE),"") -> 8 | J95: =IF(A95="","",IF(B95="",IF(TODAY()-A95>I95,"ATRASADA","EM ANDAMENTO"),IF(B95-A95>I95,"ATRASADA","NO PRAZO"))) -> NO PRAZO | K95: =Tabela2[[#This Row],[SLA Padrão]]-Tabela2[[#This Row],[SLA Atendimento]] -> 2 | M95: 55.85 | N95: 55.85 | O95: BRL | P95: =Tabela2[[#This Row],[Proposta Inicial]]-Tabela2[[#This Row],[Proposta Negociada]] -> 0 | Q95: =Tabela2[[#This Row],[Proposta Negociada]]/Tabela2[[#This Row],[Proposta Inicial]]-1 -> 0 | S95: RC 10001788 - Caixa de Farinha | T95: 450000313 | W95: 26468 | X95: Sim | Y95: Sim
A96: 46225 | B96: 46225 | C96: =IF(OR(A96="",B96=""),"",B96-A96) -> 0 | D96: Amanda Salvi | E96: CPTR | F96: Bomax no Brasil Equipamentos Industrial S/A | G96: Spot | H96: Serviço Urgente | I96: =IFERROR(VLOOKUP(H96,SLA_Ref!$A$1:$B$8,2,FALSE),"") -> 5 | J96: =IF(A96="","",IF(B96="",IF(TODAY()-A96>I96,"ATRASADA","EM ANDAMENTO"),IF(B96-A96>I96,"ATRASADA","NO PRAZO"))) -> NO PRAZO | K96: =Tabela2[[#This Row],[SLA Padrão]]-Tabela2[[#This Row],[SLA Atendimento]] -> 5 | M96: 787.37 | N96: 787.37 | O96: BRL | P96: =Tabela2[[#This Row],[Proposta Inicial]]-Tabela2[[#This Row],[Proposta Negociada]] -> 0 | Q96: =Tabela2[[#This Row],[Proposta Negociada]]/Tabela2[[#This Row],[Proposta Inicial]]-1 -> 0 | S96: Manutenção bomba pneumática Bomax | T96: 450000314 | X96: Sim | Y96: Não
A97: 46220 | B97: 46226 | C97: =IF(OR(A97="",B97=""),"",B97-A97) -> 6 | D97: Amanda Salvi | E97: CPTR | F97: Md Comercio de Ferramentas e Serviços Ltda | G97: Spot | H97: Regularização | I97: =IFERROR(VLOOKUP(H97,SLA_Ref!$A$1:$B$8,2,FALSE),"") -> 30 | J97: =IF(A97="","",IF(B97="",IF(TODAY()-A97>I97,"ATRASADA","EM ANDAMENTO"),IF(B97-A97>I97,"ATRASADA","NO PRAZO"))) -> NO PRAZO | K97: =Tabela2[[#This Row],[SLA Padrão]]-Tabela2[[#This Row],[SLA Atendimento]] -> 24 | M97: 177 | N97: 177 | O97: BRL | P97: =Tabela2[[#This Row],[Proposta Inicial]]-Tabela2[[#This Row],[Proposta Negociada]] -> 0 | Q97: =Tabela2[[#This Row],[Proposta Negociada]]/Tabela2[[#This Row],[Proposta Inicial]]-1 -> 0 | S97: REGULARIZAÇÃO - Serra Copo para Instalação Agitador Semco | T97: 450000316 | X97: Sim | Y97: Não
A98: 46225 | B98: 46226 | C98: =IF(OR(A98="",B98=""),"",B98-A98) -> 1 | D98: Amanda Salvi | E98: GEOLOGICAL EXPLORATION | F98: Caldas Fer Ltda | G98: Spot | H98: Material Urgente | I98: =IFERROR(VLOOKUP(H98,SLA_Ref!$A$1:$B$8,2,FALSE),"") -> 3 | J98: =IF(A98="","",IF(B98="",IF(TODAY()-A98>I98,"ATRASADA","EM ANDAMENTO"),IF(B98-A98>I98,"ATRASADA","NO PRAZO"))) -> NO PRAZO | K98: =Tabela2[[#This Row],[SLA Padrão]]-Tabela2[[#This Row],[SLA Atendimento]] -> 2 | M98: 880 | N98: 880 | O98: BRL | P98: =Tabela2[[#This Row],[Proposta Inicial]]-Tabela2[[#This Row],[Proposta Negociada]] -> 0 | Q98: =Tabela2[[#This Row],[Proposta Negociada]]/Tabela2[[#This Row],[Proposta Inicial]]-1 -> 0 | S98: RC 10001802 - Compra de 4 tambores de plástico 200L | T98: 450000319 | X98: Sim | Y98: Sim
A99: 46227 | B99: 46232 | C99: =IF(OR(A99="",B99=""),"",B99-A99) -> 5 | D99: Michel Bernardes | E99: CPTR | F99: Watson Marlow | G99: Spot | H99: Material Normal | I99: =IFERROR(VLOOKUP(H99,SLA_Ref!$A$1:$B$8,2,FALSE),"") -> 8 | J99: =IF(A99="","",IF(B99="",IF(TODAY()-A99>I99,"ATRASADA","EM ANDAMENTO"),IF(B99-A99>I99,"ATRASADA","NO PRAZO"))) -> NO PRAZO | K99: =Tabela2[[#This Row],[SLA Padrão]]-Tabela2[[#This Row],[SLA Atendimento]] -> 3 | M99: 49097.61 | N99: 49097.61 | O99: BRL | P99: =Tabela2[[#This Row],[Proposta Inicial]]-Tabela2[[#This Row],[Proposta Negociada]] -> 0 | Q99: =Tabela2[[#This Row],[Proposta Negociada]]/Tabela2[[#This Row],[Proposta Inicial]]-1 -> 0 | S99: Spare parts bombas CPTR | T99: 450000337 | X99: Não | Y99: Não
A100: 46223 | B100: 46232 | C100: =IF(OR(A100="",B100=""),"",B100-A100) -> 9 | D100: Michel Bernardes | E100: CPTR | F100: VANGUARDA COMERCIAL HIDRO ELETRICA "LTDA" | G100: Spot | H100: Material Normal | I100: =IFERROR(VLOOKUP(H100,SLA_Ref!$A$1:$B$8,2,FALSE),"") -> 8 | J100: =IF(A100="","",IF(B100="",IF(TODAY()-A100>I100,"ATRASADA","EM ANDAMENTO"),IF(B100-A100>I100,"ATRASADA","NO PRAZO"))) -> ATRASADA | K100: =Tabela2[[#This Row],[SLA Padrão]]-Tabela2[[#This Row],[SLA Atendimento]] -> -1 | M100: 5558.05 | N100: 5558.05 | O100: BRL | P100: =Tabela2[[#This Row],[Proposta Inicial]]-Tabela2[[#This Row],[Proposta Negociada]] -> 0 | Q100: =Tabela2[[#This Row],[Proposta Negociada]]/Tabela2[[#This Row],[Proposta Inicial]]-1 -> 0 | S100: Ventilação forçada dos motores dos agitadores | T100: 450000332 | X100: Não | Y100: Não
...

Sheet Controle RCs
A1: RC's recebidas 2026 | B1: Janeiro | C1: Fevereiro | D1: Março | E1: Abril | F1: Maio | G1: Junho | H1: Julho | I1: Agosto | J1: Setembro | K1: Outubro | L1: Novembro | M1: Dezembro | N1: TOTAL
A2: OPEX | B2: 79 | C2: 70 | D2: 109 | E2: 115 | F2: 147 | N2: 520
A3: CAPEX | B3: 56 | C3: 48 | D3: 76 | E3: 75 | F3: 37 | N3: 292
M4: TOTAL | N4: 812
A5: RC's recebidas 2026 - URGENTES | B5: Janeiro | C5: Fevereiro | D5: Março | E5: Abril | F5: Maio | G5: Junho | H5: Julho | I5: Agosto | J5: Setembro | K5: Outubro | L5: Novembro | M5: Dezembro | N5: TOTAL
A6: OPEX | B6: 33 | C6: 30 | D6: 57 | E6: 56 | F6: 83 | N6: 259
A7: CAPEX | B7: 45 | C7: 36 | D7: 59 | E7: 53 | F7: 19 | N7: 212
M8: TOTAL | N8: 471
N9: 0.58004926
N10: ~59,1%
A11: RC's Status | B11: Janeiro | C11: Fevereiro | D11: Março | E11: Abril | F11: Maio | G11: Junho | H11: Julho | I11: Agosto | J11: Setembro | K11: Outubro | L11: Novembro | M11: Dezembro | N11: TOTAL
A12: OPEX - Abertas
A13: OPEX - Concluídas
A14: CAPEX - Abertas
A15: CAPEX - Concluídas
A17: RC's recebidas 2026 REGULARIZAÇÃO | B17: Janeiro | C17: Fevereiro | D17: Março | E17: Abril | F17: Maio | G17: Junho | H17: Julho | I17: Agosto | J17: Setembro | K17: Outubro | L17: Novembro | M17: Dezembro | N17: TOTAL
A18: TOTAL | B18: - | C18: - | D18: - | E18: - | F18: 18 | N18: 18
A21: Ano | B21: RC's recebidas OPEX | C21: RC's recebidas CAPEX | D21: TOTAL RC's recebidas
A22: 2024 | B22: 464 | C22: 0 | D22: 464
A23: 2025 | B23: 598 | C23: 94 | D23: 692
A24: 2026 | B24: 251 | C24: 170 | D24: =SUM(B24:C24) -> 421

Sheet Gestão de Contratos

Sheet Cadastro Fornecedores
A1: CÓD. VIRIDIS FORNECEDOR | B1: CATEGORIA ATUALIZADA | C1: RAZÃO SOCIAL | D1: NOME FANTASIA | E1: CNPJ | F1: ENDEREÇO | G1: CIDADE | H1: UF | I1: CEP | J1: PAIS | K1: CONTATO PRINCIPAL | L1: TELEFONE | M1: E-MAIL | N1: COMPRA INTERNET | O1: FORNECEDOR LOCAL
A2: 300001 | B2: Materiais e Suprimentos Industriais | C2: GOTAGUA FILTROS LTDA | D2: GOTAGUA | E2: 06.298.134/0001--17 | F2: Alameda Dona Tereza Cristina, 46 lloja | G2: SÃO BERNARDO DO CAMPO | H2: SP | I2: 9770330 | J2: BRASIL | K2: Luiz Carlos Blasques Junior | L2: (11) 4123-6109 | M2: atendimento@gotagua.com.br | N2: SIM | O2: NÃO
A3: 300002 | B3: Equipamentos de Proteção Individual | C3: ALPHA ABRAS COMERCIO DE ABRASIVOS LTDA | D3: ALPHABRAS | E3: 05.159.343/0001-56 | F3: TRAVESSA CORONEL VIRGILIO SILVA, 102 BE, BASTOS | G3: POÇOS DE CALDAS | H3: MG | I3: 37701489 | J3: BRASIL | K3: Adriano | L3: (35) 99829-7179 | M3: adriano.alphabras@gmail.com | N3: NÃO | O3: SIM
A4: 300003 | B4: Softwares e Licenças | C4: D-SAAS TECNOLOGIA EM DESENVOLVIMENTO DE SOFTWARE LTDA | D4: DIMEP | E4: 46.220.369/0001-00 | F4: Avenida Mofarrej, n.º 840, 2º andar, Vila Leopoldina | G4: SÃO PAULO | H4: SP | I4: 5311000 | J4: BRASIL | K4: Marcelo Mariano | L4: (35) 98861-0140 | M4: prontec.marcelo@uol.com.br | N4: NÃO | O4: NÃO
A5: 300004 | B5: Fornecimento de Produtos de Limpeza | C5: DISK LIMPEZA TOTAL LTDA | D5: DISK LIMPEZA | E5: 10.757.521/0001-41 | F5: R São Paulo, 276 Centro | G5: POÇOS DE CALDAS | H5: MG | I5: 3701001 | J5: BRASIL | K5: Luciano Dias | L5: (35) 3721-2647 | M5: limpezatotal09@hotmail.com | N5: NÃO | O5: SIM
A6: 300005 | B6: Fornecedores de Alimentação | C6: PAO DE MEL E BOMBOCADO LTDA EPP | D6: BOMBOCADO | E6: 66.444.787/0003-50 | F6: R Paraiba, 182 Centro | G6: POÇOS DE CALDAS | H6: MG | I6: 37701022 | J6: BRASIL | K6: Adriana | L6: (35) 9802-1949 | N6: NÃO | O6: SIM
A7: 300006 | B7: Fornecedores de Alimentação | C7: PADARIA KI SABOR LTDA | D7: KI SABOR | E7: 05.439.722/0001-60 | F7: Avenida Espanha, 165 Parque das Naçoes | G7: POÇOS DE CALDAS | H7: MG | I7: 37706181 | J7: BRASIL | K7: Ana Cristina Pacheco | L7: (35) 3715-7404 | M7: padaria_padariakisabor@hotmail.com | N7: NÃO | O7: SIM
A8: 300007 | B8: Corretora de Imóveis | C8: AINER GESTÃO DE NEGÓCIOS E AVALIAÇÕES LTDA | D8: CENER | E8: 56.746.425/0001-07 | F8: Rua Benedito Lobato, nº 634, apto 502, bairro São João, | G8: CONSELHEIRO LAFAIETE | H8: MG | I8: 36404154 | J8: BRASIL | K8: Kathrein Maia | L8: (31) 99797-0502 | M8: KATHREINRM@HOTMAIL.COM | N8: NÃO | O8: NÃO
A9: 300008 | B9: Consultoria Técnica e Ambiental | C9: 3EM-MINERACAO E GEOLOGIA LTDA-ME | D9: 3EM | E9: 27.584.269/0001-19 | F9: Avenida Portugal, n.º 3250, loja 09 e 10, Pavimento 1, Bairro Jardim Atlântico | G9: BELO HORIZONTE | H9: MG | I9: 31560000 | J9: BRASIL | K9: Lúcio Miranda Camêlo | L9: (31) 99777-2049 | M9: lucio@3emmg.com.br | N9: NÃO | O9: NÃO
A10: 300009 | B10: Telefonia e Planos Corporativos | C10: ALGAR TELECOM S/A | D10: ALGAR | E10: 71.208.516/0001-74 | F10: Rua José Alves Garcia, n.º 415, bairro Brasil | G10: UBERLÂNDIA | H10: MG | I10: 38400668 | J10: BRASIL | K10: Vagner Manoel | L10: (43) 98801-1100 | M10: vagner.manoel@algarempresarial.com | N10: NÃO | O10: NÃO
A11: 300010 | B11: Softwares e Licenças | C11: ALGER CONSULTORIA SOCIOAMBIENTAL LTDA | D11: ALGER | E11: 40.586.743/0001-00 | F11: Rua Sebastião Fabiano Dias, 210, Salas 701 a 708, Bairro Belvedere | G11: BELO HORIZONTE | H11: MG | I11: 30320690 | J11: BRASIL | K11: Regina Cruz | L11: (31) 99812-5747 | M11: regina@algerconsultoria.com.br | N11: NÃO | O11: NÃO
A12: 300011 | B12: Marketing, Comunicação e Gráfica | C12: AMANDA CORRÊA DE MORAIS COSTA | D12: IDEOLOGICO | E12: 34.686.648/0001-85 | F12: Rua Papula Vermelha, 245, bairro Havaí | G12: BELO HORIZONTE | H12: MG | I12: 30555190 | J12: BRASIL | K12: Amanda Correa | L12: (31) 99107-4175 | M12: contato@igeologico.com.br | N12: NÃO | O12: NÃO
A13: 300012 | B13: Coleta de Resíduos Comuns e Recicláveis | C13: ANTONIO APARECIDO ALMEIDA ME (CONEXÃO SA) | D13: CONEXAO AS | E13: 30.386.654/0001-66 | F13: Rua Pedro Marcante, n.º 10, apartamento 2, bairro Boa Esperança II, | G13: POÇOS DE CALDAS | H13: MG | I13: 37704524 | J13: BRASIL | K13: Antonio Aparecido Almeida | L13: (35) 99239-8501 | M13: toninho@conexaosa.com | N13: NÃO | O13: SIM
A14: 300013 | B14: Locação de Espaços e Equipamentos | C14: ARGENTINA MALL LTDA | D14: ARGENTINA MALL | E14: 21.746.130/0001-48 | F14: Rua Barros Cobra, nº 305, Conjunto 52, Sala 02 – Centro | G14: POÇOS DE CALDAS | H14: MG | I14: 37701822 | J14: BRASIL | K14: Fernanda Pereira | L14: (35) 99984-1552 | M14: fernanda@evoluaimoveis.com.br | N14: NÃO | O14: SIM
A15: 300014 | B15: Seguros | C15: AVLA SEGUROS BRASIL S.A. (GIFT SEGUROS) | D15: AVLA | E15: 41.182.665/0001-40 | F15: Rua Olimpíadas, nº 205, cj. nº. 32, Vila Olímpia | G15: SÃO PAULO | H15: SP | I15: 4551000 | J15: BRASIL | K15: Jhonattan de Oliveira | L15: (19) 99847-3338 | M15: jhonattan@giftseguros.com | N15: NÃO | O15: NÃO
A16: 300015 | B16: Softwares e Licenças | C16: BNA EQUIPAMENTOS E SISTEMAS DO BRASIL, COMÉRCIO, IMPORTACAO E EXPORTACAO LTDA | D16: BNA | E16: 05.569.016/0001-33 | F16: Rua Desembargador Leao Starling, n.º 200, bairro Ouro Preto | G16: BELO HORIZONTE | H16: MG | I16: 31310370 | J16: BRASIL | K16: Beck Nader | L16: (31) 98438-3411 | M16: beckn@bnaconsultoria.com | N16: NÃO | O16: NÃO
A17: 300016 | B17: Escritório de Contabilidade | C17: CGC CONTABILIDADE GERAL E CONSULTORIA | D17: CGC | E17: 65.165.649/0001-08 | F17: Rua Professor Moraes, 476 - loja 04 - Bairro Savassi | G17: BELO HORIZONTE | H17: MG | I17: 30150370 | J17: BRASIL | K17: Ricardo Santos | L17: (31) 99192-5133 | M17: ricardo@cgccontabilidade.com.br | N17: NÃO | O17: NÃO
A18: 300017 | B18: Consultoria Técnica e Ambiental | C18: CLAM MEIO AMBIENTE LTDA | D18: CLAM | E18: 08.803.534/0001-68 | F18: Rua Sergipe, 1333, Sala 901, bairro Savassi | G18: BELO HORIZONTE | H18: MG | I18: 30130134 | J18: BRASIL | K18: Patricia Medeiros | L18: (31) 98379-2040 | M18: patricia.medeiros@clam.com.br | N18: NÃO | O18: NÃO
... A30: 300029 | B30: Clínicas de Medicina do Trabalho | C30: L.C.B - ATIVIDADES MEDICAS EIRELI | D30: MEDNET | E30: 36.608.298/0001-64 | F30: Rua Pernambuco, 444, Centro - Sala 4 | G30: POÇOS DE CALDAS | H30: MG | I30: 37701021 | J30: BRASIL | K30: Aline Dias | L30: (35) 99670-1143 | M30: com01@mednet-pocoscaldas.com.br | N30: NÃO | O30: SIM
A31: 300030 | B31: Monitoramento Eletrônico (Câmeras e Alarmes) | C31: LARISSA S. RODRIGUES - ME (LOTUS) | D31: LOTUS | E31: 14.022.179/0001-92 | F31: Av. Juscelino Kubitscheck de Oliveira, 46 - Parque Vivaldi Leite Ribeiro | G31: POÇOS DE CALDAS | H31: MG | I31: 37701-186 | J31: BRASIL | K31: Amanda Del Sarto | L31: (35) 99829-0087 | M31: administrativo@centraldemonitoramento24hs.com.br | N31: NÃO | O31: SIM
A32: 300031 | B32: Seguros | C32: MAPFRE SEGUROS GERAIS S.A (AJG) | D32: MAPFRE | E32: 61.074.175/0001-38 | F32: Av. das Naçoes Unidas, 14.261 - ALA A, Vila Gertrudes | G32: SÃO PAULO | H32: SP | I32: 4794000 | J32: BRASIL | K32: Eduarda Guido | L32: (11) 96596-7644 | M32: Eduarda_Guido@ajg.com> | N32: NÃO | O32: NÃO
A33: 300032 | B33: Consultoria Técnica e Ambiental | C33: MDGEO SERVIÇOS DE HIDREOLOGIA LTDA | D33: MDGEO | E33: 38.625.927/0001-90 | F33: Rua Santa Bárbara, nº 162, Sagrada Família | G33: BELO HORIZONTE | H33: MG | I33: 31030150 | J33: BRASIL | K33: Daniel Coelho | L33: (31) 3482-9959 | M33: Daniel.Coelho@mdgeo.com.br | N33: NÃO | O33: NÃO
A34: 300033 | B34: Serviços Jurídicos e de Compliance | C34: MENDES E BARSI SOCIEDADE DE ADVOGADOS | D34: MENDES E BARSI | E34: 35.377.825/0001-04 | F34: Rua Prefeito Chagas, n.º 489, sala 01, centro, | G34: POÇOS DE CALDAS | H34: MG | I34: 37701734 | J34: BRASIL | K34: Marcinha / Pri | L34: (35) 99129-7700 / (35) 99779-9000 | M34: juridico@viridismining.com.au | N34: NÃO | O34: SIM
A35: 300034 | B35: Consultoria Técnica e Ambiental | C35: PROMINAS PROJETOS E SERVIÇOS DE MINERAÇÃO LTDA | D35: PROMINAS | E35: 01.955.849/0001-81 | F35: Rua Paraíba, n.º 1465, sala 1101, 11º andar, bairro Savassi | G35: BELO HORIZONTE | H35: MG | I35: 30130148 | J35: BRASIL | K35: Marlos Roges | L35: (31) 3497-4274 | M35: marlos.roges@prominasmining.com | N35: NÃO | O35: NÃO
A36: 300035 | B36: Programas de Educação e Impacto Social | C36: RHINO PRODUÇOES LTDA | D36: O MUNDO DE RHINO | E36: 55.962.620/0001-01 | F36: Rua Capitão Afonso Junqueira, nº 240, Complemento 53, Centro | G36: POÇOS DE CALDAS | H36: MG | I36: 37701042 | J36: BRASIL | K36: Marco Noronha | L36: (35) 98821-1661 | M36: omundorhino@gmail.com | N36: NÃO | O36: SIM
A37: 300036 | B37: Tecnologia da Informação (TI) | C37: RONAN LEITE CHIMINAZO | D37: RONAN | E37: 54.737.662/0001-78 | F37: Av. Jaçanã Musa dos Santos, n.º 405, bairro Conjunto Habitacional | G37: POÇOS DE CALDAS | H37: MG | I37: 37706206 | J37: BRASIL | K37: Ronan Chiminazzo | L37: (35) 99199-5615 | M37: ronanlc@4techinformatica.com.br | N37: NÃO | O37: SIM
A38: 300037 | B38: Softwares e Licenças | C38: SEEQUENT - BENTLEY SYSTEMS BRASIL LTDA. | D38: SEEQUENT | E38: 01.712.235/0001-79 | F38: Avenida Paulista, 2537 – Bela Vista - 9 andar, sala 09-114 | G38: SÃO PAULO | H38: SP | I38: 1310100 | J38: BRASIL | K38: Ana Pinheiro | L38: (31) 99089-3270 | M38: Ana.Pinheiro@seequent.com | N38: NÃO | O38: NÃO
A39: 300038 | B39: Programas de Educação e Impacto Social | C39: SENAI - SERVIÇO NACIONAL DE APRENDIZAGEM INDUSTRIAL | D39: SENAI | E39: 03.773.700/0026-65 | F39: Rua Pedro Barbosa, n.º 600, bairro Monte Verde | G39: POÇOS DE CALDAS | H39: MG | I39: 37705309 | J39: BRASIL | K39: Gustavo Costa Mendes | L39: (35) 3729-2613 | M39: gc.mendes@fiemg.com.br | N39: NÃO | O39: SIM
A40: 300039 | B40: Química e Análises Laboratoriais | C40: SIEVERT LABORATÓRIO E SERVIÇOS AMBIENTAIS LTDA, | D40: SIEVERT | E40: 06.960.855/0001-40 | F40: Rua Olavio Virgílio dos Santos, n.º 31, bairro Vila Califórnia | G40: SÃO PAULO | H40: SP | I40: 4775220 | J40: BRASIL | K40: Priscila Nogueira | L40: (19) 98455-9001 | M40: vendas@glplab.com.br | N40: NÃO | O40: NÃO
A41: 300040 | B41: Locação de Veículos | C41: TERRAPLENAGEM PAULA E COSTA LTDA ME | D41: PAULA E COSTA | E41: 11.009.825/0001-93 | F41: Avenida Doutor Ubirajara Machado de Moraes, n.º 636, bairro Jd. Nova Aparecida | G41: POÇOS DE CALDAS | H41: MG | I41: 37704016 | J41: BRASIL | K41: Wilson Reis | L41: (35) 99191-0061 | M41: pcterraplanagem@hotmail.com | N41: NÃO | O41: SIM
A42: 300041 | B42: Locação de Espaços e Equipamentos | C42: VSTAY GESTAO IMOBILIARIA LTDA | D42: VSTAY | E42: 53.709.633/0001-30 | F42: Rua Capitão Afonso Junqueira, 290, Sala 05, Centro | G42: POÇOS DE CALDAS | H42: MG | I42: 37701042 | J42: BRASIL | K42: Thiago Muniz | L42: (35) 98401-9369 | M42: thiago@construtoravital.com | N42: NÃO | O42: SIM
A43: 300042 | B43: Marketing, Comunicação e Gráfica | C43: SEMPRE EDITORA LTDA | D43: JORNAL O TEMPO | E43: 26.198.515/0004-84 | F43: Avenida Babita Camargos, 1645 Cidade Industrial | G43: CONTAGEM | H43: MG | I43: 32210180 | J43: BRASIL | K43: Mirian Andrade | L43: (31) 8347-8576 | M43: mirian.santo@otempo.com.br | N43: NÃO | O43: NÃO
A44: 300043 | B44: Locação de Firewall | C44: BLUEPEX TECNOLOGIA S.A. | D44: BLUEPEX | E44: 02.227.843/0001-50 | F44: Rua Wilson Vitório Coletta, 157 | G44: LIMEIRA | H44: SP | I44: 13482225 | J44: BRASIL | L44: (35) 98818-2228 | M44: larissa.venancio@bluepex.com | N44: NÃO | O44: NÃO
A45: 300044 | B45: Fornecedores de Alimentação | C45: SODRE MIGUEL LTDA | D45: SAN MICHEL | E45: 19.709.344/0001-00 | F45: Rua Pernambuco, 1000 Centro | G45: POÇOS DE CALDAS | H45: MG | I45: 37701021 | J45: BRASIL | L45: (35) 3729-1515 | N45: NÃO | O45: SIM
A46: 300045 | B46: Materiais e Suprimentos Industriais | C46: SOUZA & MONTEIRO LTDA | D46: LOJA DO VARAL | E46: 03.208.846/0001-00 | F46: Rua Correa Neto, 256 Centro | G46: POÇOS DE CALDAS | H46: MG | I46: 37701016 | J46: BRASIL | L46: (35) 3714-1777 | N46: NÃO | O46: SIM
A47: 300046 | B47: Materiais e Suprimentos Industriais | C47: SUPRITEC TECNOLOGIA EM SEGURANÇA LTDA | D47: SUPRITEC | E47: 08.268.970/0004-27 | F47: Rua Vereador Joao Siqueira Loyola, Jd Campos Eliseos | G47: POÇOS DE CALDAS | H47: MG | I47: 37706029 | J47: BRASIL | K47: Guilherme | L47: (35) 9811-2215 | M47: guilherme.faria@gruposupritec.com.br | N47: NÃO | O47: SIM
A48: 300047 | B48: Fornecimento de Combustíveis e Lubrificantes | C48: MAXIMA SHOP | D48: MAXIMASHOP. COM COMERCIAL EIRELI | E48: 15.392.064/0001-52 | F48: Rua Antonio Coelho dos Santos, 37 Boqueirao | G48: CURITIBA | H48: PR | I48: 81750140 | J48: BRASIL | L48: (41) 8807-7755 | N48: SIM | O48: NÃO
A49: 300048 | B49: Fornecedores de Alimentação | C49: CENTERNARIO EXPRESS | D49: CENTENARIO EXPRESS LTDA | E49: 56.908.192/0001-93 | F49: Rua Argentina, 455 Jd Quisisana | G49: POÇOS DE CALDAS | H49: MG | I49: 37701248 | J49: BRASIL | N49: NÃO | O49: SIM
A50: 300049 | B50: Materiais e Suprimentos Industriais | C50: LOGMAIS ETIQUETAS ADESIVAS LTDA | D50: LOGGMAIS | E50: 42.287.977/0001-81 | F50: Rua Vicente de Carvalho, 134 Sala 1 | G50: CAMBUCI | H50: SP | I50: 1521020 | J50: BRASIL | N50: SIM | O50: NÃO
A51: 300050 | B51: Tecnologia da Informação (TI) | C51: TUDO SOBRE ELETRONICOS LTDA | D51: TUDO SOBRE ELETRONICOS LTDA | E51: 55.602.536/0001-79 | F51: Rua Manuel Gaya, 620 CP 13014, Vila Nova Mazzei | G51: SÃO PAULO | H51: SP | I51: 2313970 | J51: BRASIL | N51: SIM | O51: NÃO
A52: 300051 | B52: Brindes | C52: TUDO BR DISTRIBUIDORA LTDA | D52: TUDO BR DISTRIBUIDORA LTDA | E52: 37.196.468/0001-03 | F52: Rua Cristo Redentor, 699 Vila Rezende | G52: PIRACICABA | H52: SP | I52: 13405269 | J52: BRASIL | N52: SIM | O52: NÃO
A53: 300052 | B53: Materiais e Suprimentos Industriais | C53: MCR TOTTI LTDA | D53: MCR TOTTI LTDA | E53: 25.958.668/0002-58 | F53: Via Anhanguera S/N KM 25.5 Lateral 1 | G53: SÃO PAULO | H53: SP | I53: 5275000 | J53: BRASIL | N53: SIM | O53: NÃO
A54: 300053 | B54: Marketing, Comunicação e Gráfica | C54: COPIATIVA DIGITAL | D54: VERONESI & FILHOS LTDA | E54: 25.853.615/0002-72 | F54: Rua Santa Catarina, 184 Centro | G54: POÇOS DE CALDAS | H54: MG | I54: 37701750 | J54: BRASIL | K54: Gabriel | L54: (35) 8707-1252 | M54: producao@copiativadigital.com.br | N54: NÃO | O54: SIM
A55: 300054 | B55: Materiais e Suprimentos Industriais | C55: PLASTIPOCOS | D55: PLASTIPOCOS LTDA | E55: 64.474.380/0001-89 | F55: Rua Pernambuco Mercado Municipal, SN LJ 5 31-32 Centro | G55: POÇOS DE CALDAS | H55: MG | I55: 37701021 | J55: BRASIL | L55: (35) 9670-2163 | N55: NÃO | O55: SIM
A56: 300055 | B56: EPIs e EPCs | C56: MG GLOVERS | D56: MG GLOVERS IND. E COM. DE EPI E SUPRIMENTOS INDUSTRIAIS LTDA | E56: 27.510.292/0001-69 | F56: Rua Maestro Fransciso Nistico, 46 Unid. 04 São Vicente | G56: ITAJUBA | H56: MG | I56: 37502060 | J56: BRASIL | L56: (35) 2143-1249 | N56: SIM | O56: NÃO
A57: 300056 | B57: Tecnologia da Informação (TI) | C57: DELL | D57: DELL COMPUTADORES DO BRASIL LTDA | E57: 72.381.189/0010-01 | F57: Avenida da Emancipacao, 5000 Parte B Parque dos Pinheiros | G57: HORTOLANDIA | H57: SP | I57: 13184654 | J57: BRASIL | K57: Brenda Valenthyna | L57: (11) 98928-8870 | M57: brenda.valenthyna@dell.com | N57: SIM | O57: NÃO
A58: 300057 | B58: Tecnologia da Informação (TI) | C58: GEOTRACK | D58: GEOTRACK COMERCIO IMPORTACAO E DISTRIBUICAO LTDA | E58: 07.560.148/0001-20 | F58: Avenida Olimpio Prates, 577 Letra A Major Prates | G58: MONTES CLAROS | H58: MG | I58: 39403261 | J58: BRASIL | L58: (38) 3216-1715 | N58: SIM | O58: NÃO
A59: 300058 | B59: Fornecimento de Produtos de Limpeza | C59: RAIA DROGASIL S/A | D59: RAIA DROGASIL S/A | E59: 61.585.865/1318-41 | F59: Avenida Santo Antonio, 252 Jardim Cascatinha | G59: POÇOS DE CALDAS | H59: MG | I59: 37701036 | J59: BRASIL | L59: (35) 99805-0887 | N59: NÃO | O59: SIM
A60: 300059 | B60: EPIs e EPCs | C60: VICOM TECNOLOGIA | D60: VICOM TECNOLOGIA BRASIL LTDA | E60: 19.467.066/0001-14 | F60: Avenida das Americas, 3443 | G60: RIO DE JANEIRO | H60: RJ | I60: 22631003 | J60: BRASIL | K60: Victor | L60: (21) 96435-7164 | N60: SIM | O60: NÃO
A61: 300060 | B61: Materiais e Suprimentos Industriais | C61: ART PEL | D61: PAPELARIA BOMPAPEL LTDA | E61: 71.332.779/0001-90 | F61: Rua Rio de Janeiro, 121 Centro | G61: POÇOS DE CALDAS | H61: MG | I61: 37701011 | J61: BRASIL | K61: Camila | L61: (35) 8468-3833 | M61: gerenciabp@hotmail.com | N61: NÃO | O61: SIM
A62: 300061 | B62: Materiais e Suprimentos Industriais | C62: BRASIL MINAS UNIFORMES | D62: BRASIL MINAS UNIFORMES PROFISSIONAIS LTDA | E62: 71.424.998/0001-08 | F62: Rua Castro Alves, 2605 Irmaos Auler | G62: ITAUNA | H62: MG | I62: 35680095 | J62: BRASIL | K62: Tainara | L62: (37) 9908-6346 | M62: tainara.oliveira@brasilminasuniformes.com.br | N62: NÃO | O62: NÃO
A63: 300062 | B63: Fornecedores de Alimentação | C63: LUCIENY MARQUES SANTOS | D63: TRIGO BOM | E63: 20.299.217/0001-51 | F63: Rua Jose Augusto de Carvalho, 15 São Jose | G63: POÇOS DE CALDAS | H63: MG | I63: 37704251 | J63: BRASIL | L63: (35) 99700-6990 | N63: NÃO | O63: SIM
A64: 300063 | B64: Seguros | C64: CHUBB SEGUROS BRASIL S.A. | D64: CHUBB | E64: 33.170.085/0001-05 | F64: Av. Rebouças, 3.970, 25° ao 28° andares | G64: SÃO PAULO | H64: SP | I64: 5402920 | J64: BRASIL | K64: Diego / Quéren | L64: (31) 99438 7933 | M64: Diego.Antonio@marsh.com | N64: NÃO | O64: NÃO
A65: 300064 | B65: Chaveiro | C65: CHAVEIRO ALERTA LTDA | D65: CHAVEIRO ALERTA | E65: 14.973.819/0002-20 | F65: Rua Assis Figueiredo, 791, Centro | G65: POÇOS DE CALDAS | H65: MG | I65: 37701000 | J65: BRASIL | L65: (35)3722-6355 | N65: NÃO | O65: SIM
A66: 300065 | B66: Fornecedores de Alimentação | C66: AGUAS MINEIRAIS POCOS DE CALDAS LTDA | D66: AGUA POCOS DE CALDAS | E66: 19.567.510/0001-73 | F66: Rua Piaui, 2 Centro | G66: POÇOS DE CALDAS | H66: MG | I66: 37701024 | J66: BRASIL | K66: Glaucia | L66: (35) 98848-3116 | M66: comercial@aguapocosdecaldas.com.br | N66: NÃO | O66: SIM
A67: 300066 | B67: Recuperação de Áreas Degradadas | C67: MADEIREIRA IRMAOS FIGUEIREDO LTDA | D67: MADEIREIRA IRMAOS FIGUEIREDO | E67: 20.364.220/0001-01 | F67: Rua Senador Salgado Filho, 765 Jd Country Club | G67: POÇOS DE CALDAS | H67: MG | I67: 37701352 | J67: BRASIL | K67: Paulo | L67: (35) 9671-7556 | N67: NÃO | O67: SIM
A68: 300067 | B68: Marketing, Comunicação e Gráfica | C68: CAROLINI CRISTINA ARAUJO DE SOUZA | D68: MASTERS | E68: 54.924.086/0001-78 | F68: Rua Barao do Campo Mistico, 80 Comercio 301 Bairro dos Funcionarios | G68: POÇOS DE CALDAS | H68: MG | I68: 37701039 | J68: BRASIL | K68: Carolini | L68: (35) 9106-5670 | N68: NÃO | O68: SIM
A69: 300068 | B69: Mobiliário e Infraestrutura | C69: CONTABILISTA SUPRIMENTOS PARA ESCRITORIO S/A | D69: CONTABILISTA SUPRIMENTOS PARA ESCRITORIO S/A | E69: 77.765.840/0001-70 | F69: Rua Jose Batista dos Santos, 2951 Cidade Industrial | G69: CURITIBA | H69: PR | I69: 81250000 | J69: BRASIL | L69: (41) 3330-8000 | M69: faleconosco@contabilista.com.br | N69: SIM | O69: NÃO
A70: 300069 | B70: Transportes e Logística | C70: PAULINERIS TRANSPORTES E ENCOMENDAS LT | D70: PAULINERIS | E70: 42.846.634/0001-00 | F70: Rua Tatuim, 305 Vila Teixeira | G70: ALFENAS | H70: MG | I70: 37132418 | J70: BRASIL | K70: Ramon | L70: (31) 2104-5677 | N70: NÃO | O70: NÃO
A71: 300070 | B71: Marketing, Comunicação e Gráfica | C71: VERONESI & FILHOS LTDA | D71: SIMCO | E71: 25.853.615/0001-91 | F71: Rua São Paulo, 251 Centro | G71: POÇOS DE CALDAS | H71: MG | I71: 37701752 | J71: BRASIL | L71: (35) 8707-1253 | M71: simcocopiadora@hotmail.com | N71: NÃO | O71: SIM
A72: 300071 | B72: Consultoria Técnica e Ambiental | C72: MATHEUS RESENDE VICENTINI | D72: MAAT GE | E72: 45.441.585/0001-13 | F72: Rua Batista de Castro, 107, Vila Santa Teresinha | G72: SAO JOAO DEL REI | H72: MG | I72: 36305-190 | J72: BRASIL | K72: Leandro | L72: (31) 99177-1321 | M72: maat.ge@outlook.com | N72: NÃO | O72: NÃO
A73: 300072 | B73: Softwares e Licenças | C73: DOCUSIGN BRASIL SOLUCOES EM TECNOLOGIA LTDA | D73: DOCUSIGN | E73: 18.520.848/0001-07 | F73: Avenida Jornalista Roberto Marinho, 85 - Cidade Moncoes | G73: SÃO PAULO | H73: SP | I73: 04576-010 | J73: BRASIL | K73: Carolina Ogando | L73: (11) 3330-1000 | M73: carolina.ogando@docusign.com | N73: NÃO | O73: NÃO
A74: 300073 | B74: Manutenção Industrial e Mecânica | C74: PONTUAL MARTINS LTDA | D74: GRAND PNEUS | E74: 09.343.660/0003-01 | F74: Avenida João Pinheiro, 777 Campo da Mogiana | G74: POÇOS DE CALDAS | H74: MG | I74: 37701880 | J74: BRASIL | K74: Carla | L74: (35) 9912-7084 | N74: NÃO | O74: SIM
A75: 300074 | B75: Fornecedores de Alimentação | C75: SUPERM IRMAOS ALEMIDA CENTRO LTDA | D75: SUPERMERCADO IRMAOS ALMEIDA | E75: 22.251.565/0001-84 | F75: Rua Paraiba, 805 Centro | G75: POÇOS DE CALDAS | H75: MG | I75: 37701022 | J75: BRASIL | N75: NÃO | O75: SIM
A76: 300075 | B76: Fornecedores de Alimentação | C76: MARTINS E DAMAS LTDA | D76: ROTINA CAFÉ | E76: 42.945.428/0001-57 | F76: Rua Itabira, 49 Cristiano Osorio | G76: POÇOS DE CALDAS | H76: MG | I76: 37701030 | J76: BRASIL | L76: (35) 8880-0422 | N76: NÃO | O76: SIM
A77: 300076 | B77: Fornecedores de Alimentação | C77: MART MINAS DISTRIBUIÇAO LTDA | D77: MART MINAS | E77: 04.737.552/00042-06 | F77: Avenida Alcoa, 1113 Jardim Paraiso | G77: POÇOS DE CALDAS | H77: MG | I77: 37706178 | J77: BRASIL | N77: NÃO | O77: SIM
A78: 300077 | B78: Marketing, Comunicação e Gráfica | C78: LAYOUT GRAFICA RAPIDA LTDA | D78: LAYOUT | E78: 07.761.129/0001-61 | F78: Rua Prefeito Chagas, 81 Escritorio Centro | G78: POÇOS DE CALDAS | H78: MG | I78: 37701010 | J78: BRASIL | K78: Celso | L78: (35) 3721-1838 | M78: layoutgr@layoutgr.com.br | N78: NÃO | O78: SIM
A79: 300078 | B79: Materiais e Suprimentos Industriais | C79: EMBALAGENS BR LTDA | D79: EMBALAGENS BR LTFA | E79: 37.263.044/0001-14 | F79: Rua Presidente Rosevelt, 327 Jardim Cascatinha | G79: POÇOS DE CALDAS | H79: MG | I79: 37701176 | J79: BRASIL | K79: Flávia | L79: (35) 9197-2869 | M79: flaviasgprocopio@hotmail.com | N79: NÃO | O79: SIM
A80: 300079 | B80: Marketing, Comunicação e Gráfica | C80: PROPORSOM AUDIOVISUAL LTDA | D80: PROPOSOM | E80: 12.600.572/0001-90 | F80: Rua Humberto Corigliano, 302 Jardim Aeroporto | G80: POÇOS DE CALDAS | H80: MG | I80: 37706258 | J80: BRASIL | K80: Antônio | L80: (35) 9987-1519 | N80: NÃO | O80: SIM
A81: 300080 | B81: Materiais e Suprimentos Industriais | C81: PS EMPILHADEIRAS LTDA ME | D81: PS EMPILHADEIRAS | E81: 08.620.006/0001-73 | F81: Rua Sem Denominação (Rod. Mitsui), 2143, Fazenda Campo Alegre | G81: POÇOS DE CALDAS | H81: MG | I81: 37701970 | J81: BRASIL | K81: Ramon | L81: (35) 9193-4137 | N81: NÃO | O81: SIM
A82: 300081 | B82: Serviços de Reformas e Manutenção de Escritórios | C82: RNG COMERCIO DE MOVEIS E DECORACAO LTDA | D82: INNOVA PLANEJADOS | E82: 20.207.682/0001-15 | F82: Avenida João Pinheiro, 225 Centro | G82: POÇOS DE CALDAS | H82: MG | I82: 37701386 | J82: BRASIL | K82: Raphael | L82: (35) 99191-7750 | N82: NÃO | O82: SIM
A83: 300082 | B83: Chaveiro | C83: JM CHAVEIROS LTDA ME | D83: JM CHAVEIROS | E83: 17.251.475/0001-53 | F83: Rua Assis Figureiredo, 1220 Loja 01 | G83: POÇOS DE CALDAS | H83: MG | I83: 37701706 | J83: BRASIL | L83: (35) 4141-2280 | N83: NÃO | O83: SIM
A84: 300083 | B84: Marketing, Comunicação e Gráfica | C84: CANVA PTY. LTDA | D84: CANVA | F84: 110 Kippax St. Surry Hills NSW 2010 Australia | G84: SIDNEY | H84: SE | J84: AUSTRALIA | N84: SIM | O84: NÃO
A85: 300084 | B85: Fornecimento de Produtos de Limpeza | C85: COMPANHIA DA LIMPEZA LTDA | D85: LIMPEZA & CIA | E85: 14.302.235/0001-42 | F85: Av Francisco Salles, 998 | G85: POÇOS DE CALDAS | H85: MG | I85: 37701700 | J85: BRASIL | L85: (35) 3714-7096 | N85: NÃO | O85: SIM
A86: 300093 | B86: Transportes e Logística | C86: GILSON ALVES RODRIGUES | D86: GILSON ALVES RODRIGUES | E86: 59.818.345/0001-08 | G86: POÇOS DE CALDAS | H86: MG | J86: BRASIL | K86: Gilson | L86: (35) 9840-9969 | N86: NÃO | O86: SIM
A87: 300095 | B87: Materiais e Suprimentos Industriais | C87: FITASUL - PRODUTOS DE EMBALAGEM LTDA | D87: FITASUL - PRODUTOS DE EMBALAGEM LTDA | E87: 18.164.603/0001-94 | F87: Rua Rio Amazonas, 383 Weissopolis | G87: PINHAIS | H87: PR | I87: 83322-040 | J87: BRASIL | L87: (41) 99270-7812 | N87: SIM | O87: NÃO
A88: 300096 | B88: Materiais e Suprimentos Industriais | C88: MARCELINO E MARCELINO LTDA ME | D88: SUPER 1,99 DO TCHE | E88: 06.296.601/0001-70 | F88: Rua Marechal Deodoro, 50/54 Centro | G88: POÇOS DE CALDAS | H88: MG | I88: 37701-014 | J88: BRASIL | L88: (35) 3721-8444 | N88: SIM | O88: SIM
A89: 300097 | B89: Fornecedores de Alimentação | C89: SODRE MIGUEL LTDA | D89: SAN MICHEL | E89: 19.709.344/0010-93 | F89: Avenida Irradiação, 155 Jardim Quisisana | G89: POÇOS DE CALDAS | H89: MG | J89: BRASIL | L89: (35) 3729-1515 | N89: NÃO | O89: SIM
A90: 300098 | B90: Fornecedores de Alimentação | C90: JOANAS LANCHONETE E EVENTOS LTDA | D90: JOANAS | E90: 53.099.751/0001-73 | F90: Avenida Professor Magda Pinto Amarante, 72 Jardim Hortencia | G90: POÇOS DE CALDAS | H90: MG | I90: 37705-000 | J90: BRASIL | K90: Nathalia | L90: (35) 9148-3309 | N90: NÃO | O90: SIM
A91: 300099 | B91: Fornecedores de Alimentação | C91: CORDEIRO E RAMOS LTDA EPP | D91: PAO PAO | E91: 09.161.981/0001-23 | F91: Rua Assis Figureiredo, 00215 Centro | G91: POÇOS DE CALDAS | H91: MG | I91: 37701-000 | J91: BRASIL | L91: (35) 3734-1099 | N91: NÃO | O91: SIM
A92: 300100 | B92: Fornecimento de Produtos de Limpeza | C92: CHEGOU STORE LTDA | D92: CHEGOU STORE LTDA | E92: 50.057.704/0001-79 | F92: Avenida Professora Carmem Carneiro, 1110 Sala 1 Parque Aeroporto Campos dos Goytacazes | G92: RIO DE JANEIRO | H92: RJ | I92: 28083510 | J92: BRASIL | L92: (22) 99877-0201 | N92: SIM | O92: NÃO
A93: 300101 | B93: Fornecimento de Produtos de Limpeza | C93: IDEAL EMBALAGENS FESTAS PIOLI LTDA | D93: IDEAL EMBALAGENS FESTAS PIOLI LTDA | E93: 36.665.802/0001-68 | F93: Rua Correa Neto, 566 Centro | G93: POÇOS DE CALDAS | H93: MG | I93: 37701016 | J93: BRASIL | L93: (35) 3414-4667 | N93: NÃO | O93: SIM
A94: 300103 | B94: Alojamentos e Hospedagem de Trabalhadores | C94: BORGETTHI & QUINTEIRO HOTEIS LTDA | D94: VILLA FIORI | E94: 34.699.616/0001-14 | F94: Praça Dom Pedro II, 184 | G94: POÇOS DE CALDAS | H94: MG | I94: 37701-035 | J94: BRASIL | K94: Elaine | L94: (35) 31149090 | M94: Carol <reservas@hotelvillafiori.com.br> | N94: NÃO | O94: SIM
A95: 300104 | B95: Materiais e Suprimentos Industriais | C95: LARICYS ACESSORIOS | D95: LARICYS ACESSORIOS | E95: 55.688.995/0001-17 | F95: Avenida Rui Barbosa, 26-03, Centro | G95: QUATA | H95: SP | I95: 19780005 | J95: BRASIL | L95: (18) 3569-8521 | N95: SIM | O95: NÃO
A96: 300106 | B96: Tecnologia da Informação (TI) | C96: AGIS EQUIP. E SERV INFORMATICA LTDA | D96: AGIS EQUIP. E SERV INFORMATICA LTDA | E96: 68.993.641/0008-02 | F96: Av. setecentos S/N Qd 17 sala 09 | G96: SERRA | H96: ES | I96: 29161414 | J96: BRASIL | L96: (19) 3756-4606 | N96: SIM | O96: NÃO
A97: 300107 | B97: Tecnologia da Informação (TI) | C97: SISTEMA INFORMATICA COM IMP EXP LTDS | D97: SISTEMA INFORMATICA COM IMP EXP LTDS | E97: 22.204.648/0001-12 | F97: Rua Rio de Janeiro, 514 Centro | G97: POÇOS DE CALDAS | H97: MG | I97: 37701-011 | J97: BRASIL | K97: Felipe | L97: (35) 3722-4441 | M97: felipe@sistemainformatica.com.br | N97: NÃO | O97: SIM
A98: 300108 | B98: Refrigeração e Ar Condicionado | C98: RJ AR CONDICIONADO E ENGENHARIA LTDA | D98: RJ AR CONDICIONADO E ENGENHARIA LTDA | E98: 37.963.215/0001-18 | F98: Rua Piaui, 655 Centro | G98: POÇOS DE CALDAS | H98: MG | I98: 37701024 | J98: BRASIL | K98: Cristiane | L98: (35) 99243-7789 | M98: administracao@rjarcondicionado.com | N98: SIM | O98: SIM
A99: 300109 | B99: Refrigeração e Ar Condicionado | C99: RJ AR CONDICIONADO E ENGENHARIA LTDA | D99: RJ AR CONDICIONADO E ENGENHARIA LTDA | E99: 37.963.215/0001-18 | F99: Rua Piaui, 655 Centro | G99: POÇOS DE CALDAS | H99: MG | I99: 37701024 | J99: BRASIL | K99: Cristiane | L99: (35) 99243-7789 | M99: administracao@rjarcondicionado.com | N99: NÃO | O99: SIM
A100: 300110 | B100: Consultoria Técnica e Ambiental | C100: FUNDAÇAO CENTROS DE REFERENCIA EM TECNOLOGIAS INOVADORAS | D100: FUNDAÇAO CENTROS DE REFERENCIA EM TECNOLOGIAS INOVADORAS | E100: 78.626.363/0001-24 | F100: Campus Universitário, s/n Setor C Bairro Trindade | G100: FLORIANOPOLIS | H100: SC | I100: 88040-900 | J100: BRASIL | N100: NÃO | O100: NÃO
A101: 300111 | B101: Marketing, Comunicação e Gráfica | C101: A. ALMEIDA ANTONIO PUBLICIDADE | D101: A. ALMEIDA ANTONIO PUBLICIDADE | E101: 53.126.388/0001-38 | F101: R Agrim Sugaya, 391 apto 107 Colonia | G101: SÃO PAULO | H101: SP | I101: 08260-030 | J101: BRASIL | K101: Anderson | L101: (11) 98853-8779 | N101: NÃO | O101: NÃO
A102: 300112 | B102: Locação de Espaços e Equipamentos | C102: PIXEL TOPOGRAFIA | D102: PIXEL TOPOGRAFIA | F102: Rua Capitão Afonso Junqueira, 578 | G102: POÇOS DE CALDAS | H102: MG | J102: BRASIL | K102: Marcos Resende | L102: (35) 9946-6253 | N102: SIM | O102: SIM
A103: 300113 | B103: Consultoria Técnica e Ambiental | C103: TRUE MINE LTDA | D103: TRUE MINE LTDA | E103: 57.534.336/0001-51 | F103: Al Leopoçdo de Bulhoes, 576 quadra 52 | G103: GOIANIA | H103: GO | I103: 74820060 | J103: BRASIL | N103: NÃO | O103: NÃO
A104: 300114 | B104: Consultoria Técnica e Ambiental | C104: LUIS FERNANDO PATREZI | D104: SUL MINAS TV | E104: 51.021.184/0001-07 | F104: Rua São Paulo, 545 Centro | G104: POÇOS DE CALDAS | H104: MG | I104: 37701012 | J104: BRASIL | K104: Silas | L104: (35) 9129-2922 | N104: NÃO | O104: SIM
A105: 300115 | B105: Materiais e Suprimentos Industriais | C105: COMERCIAL ART PEL LTDA | D105: ART PEL | E105: 46.292.993/0001-13 | F105: Rua Assis Figueiredo, 674, 2 Centro | G105: POÇOS DE CALDAS | H105: MG | I105: 37701000 | J105: BRASIL | L105: (35) 3722-1334 | N105: NÃO | O105: SIM
A106: 300116 | B106: Marketing, Comunicação e Gráfica | C106: SILAS FERREIRA DE BARROS BARBOSA | D106: SILAS FERREIRA DE BARROS BARBOSA | E106: 36.420.010/0001-23 | F106: Da Consolaçao, 256 Santo Andre | G106: POÇOS DE CALDAS | H106: MG | I106: 37704-041 | J106: BRASIL | K106: Silas | L106: (35) 98439-7358 | N106: NÃO | O106: SIM
A107: 300117 | B107: Materiais e Suprimentos Industriais | C107: LUITEX MAQUINAS E FERRAMENTAS LTDA | D107: LUITEX MAQUINAS E FERRAMENTAS LTDA | E107: 51.051.811/0004-03 | F107: Rua Ulisses Leme, 1850 Parque Guainco | G107: MOGI GUAÇU | H107: MG | I107: 13844-282 | J107: BRASIL | K107: Matheus | L107: (11) 95993-6026 | M107: vendas4.mogi@luitex.com.br | N107: NÃO | O107: NÃO
A108: 300118 | B108: Consultoria Técnica e Ambiental | C108: WILLIAM EDUARDO FREIRE ADVOGADOS ASSOCIADOS | D108: WILLIAM EDUARDO FREIRE ADVOGADOS ASSOCIADOS | E108: 01.413.102/0001-00 | F108: Ave Afonso Pena, 4100 Andar 12 | G108: CRUZEIRO | H108: MG | I108: 30130-009 | J108: BRASIL | L108: (31) 3261-7747 | N108: NÃO | O108: NÃO
A109: 300119 | B109: Materiais e Suprimentos Industriais | C109: CLARA ACESSORIOS | D109: CLARA ACESSORIOS | E109: 57.581.975/0001-78 | F109: Avenida Doutor Cerávolo, 6-951 | G109: PRESIDENTE PRUDENTE | H109: SP | I109: 19130-020 | J109: BRASIL | L109: (18) 3225-9852 | N109: SIM | O109: NÃO
A110: 300120 | B110: Brindes | C110: THAMIRES YASMIN SILVA NASCIMENTO | D110: THAMIRES YASMIN SILVA NASCIMENTO | E110: 51.548.871/0001-85 | F110: Avenida Gabriela Ferreira do Bem, 285 Casa | G110: POÇOS DE CALDAS | H110: MG | I110: 37714-669 | J110: BRASIL | K110: Thamires | L110: (35) 99152-9099 | N110: NÃO | O110: SIM
A111: 300121 | B111: Materiais e Suprimentos Industriais | C111: MTAG ETIQUETAS ACESSORIOS EM GERAL LTDA | D111: MTAG ETIQUETAS ACESSORIOS EM GERAL LTDA | E111: 51.075.131/0001-56 | F111: Rua Antonio Luis Fornazin, 308 Jd Dona Regina | G111: SANTA BARBARA D OESTE | H111: SP | I111: 13455745 | J111: BRASIL | L111: (19) 99451-4845 | N111: SIM | O111: NÃO
...

Sheet RCs
A1: Ano | B1: Mês | C1: Nº Mês | D1: Indicador | E1: Categoria | F1: Quantidade
A2: 2026 | B2: Janeiro | C2: 1 | D2: RC Recebidas | E2: OPEX | F2: 79
A3: 2026 | B3: Janeiro | C3: 1 | D3: RC Recebidas | E3: CAPEX | F3: 56
A4: 2026 | B4: Janeiro | C4: 1 | D4: RC Urgentes | E4: OPEX | F4: 33
A5: 2026 | B5: Janeiro | C5: 1 | D5: RC Urgentes | E5: CAPEX | F5: 45
A6: 2026 | B6: Fevereiro | C6: 2 | D6: RC Recebidas | E6: OPEX | F6: 70
A7: 2026 | B7: Fevereiro | C7: 2 | D7: RC Recebidas | E7: CAPEX | F7: 48
A8: 2026 | B8: Fevereiro | C8: 2 | D8: RC Urgentes | E8: OPEX | F8: 30
A9: 2026 | B9: Fevereiro | C9: 2 | D9: RC Urgentes | E9: CAPEX | F9: 36
A10: 2026 | B10: Março | C10: 3 | D10: RC Recebidas | E10: OPEX | F10: 109
A11: 2026 | B11: Março | C11: 3 | D11: RC Recebidas | E11: CAPEX | F11: 76
A12: 2026 | B12: Março | C12: 3 | D12: RC Urgentes | E12: OPEX | F12: 57
A13: 2026 | B13: Março | C13: 3 | D13: RC Urgentes | E13: CAPEX | F13: 59
... A21: 2026 | B21: Maio | C21: 5 | D21: RC Urgentes | E21: CAPEX | F21: 19

Sheet Evolução RCs
A1: Ano | B1: RC's Recebidas OPEX | C1: RC's Recebidas CAPEX
A2: 2024 | B2: 464 | C2: 0 | D2: =SUM(B2:C2) -> 464
A3: 2025 | B3: 598 | C3: 94 | D3: =SUM(B3:C3) -> 692
A4: 2026 | B4: 251 | C4: 170 | D4: =SUM(B4:C4) -> 421

Sheet Planilha1
A1: Spot | B1: Material Urgente | C1: 3 | D1: Amanda Salvi | F1: ADMINISTRATIVE
A2: Contrato | B2: Material Normal | C2: 8 | D2: Michel Bernardes | F2: CAPEX
B3: Serviço Urgente | C3: 5 | D3: Leandro Abreu | F3: COMMUNICATION
B4: Serviço Normal | C4: 15 | D4: Júlia Guidorizzi | F4: COMMUNITY RELATIONS
B5: Regularização | C5: 30 | F5: CPTR
B6: Contrato Contínuo Simples | C6: 30 | F6: EXECUTIVE MANAGEMENT
B7: Contrato Contínuo Complexo | C7: 60 | F7: FINANCE
B8: Importação | C8: 20 | F8: GEOLOGICAL EXPLORATION
F9: HSE
F10: HUMAN RESOURCES
F11: LEGAL
F12: MINE PLANNING
F13: PROJECTS
F14: PURCHASING
F15: REGULATORY
F16: SUSTAINABILITY
F17: IT
F18: ENVIRONMENT
F19: MKT

Sheet SLA_Ref
A1: Material Urgente | B1: 3
A2: Material Normal | B2: 8
A3: Serviço Normal | B3: 15
A4: Serviço Urgente | B4: 5
A5: Regularização | B5: 30
A6: Contrato Contínuo Simples | B6: 30
A7: Contrato Contínuo Complexo | B7: 60
A8: Importação | B8: 20
